Workbook

Sheet Tenant Data
A1: Tenant | B1: SF | C1: Rent/yr/sf | D1: Base Year Stop | E1: Lease Start Month | F1: Lease Term (years) | G1: Rent Steps
A2: Tenant A | B2: 35000 | C2: 45 | D2: $10.00/sf | E2: Jan-25 | F2: 10 | G2: 3%/year
A3: Tenant B | B3: 30000 | C3: 41 | D3: Percentage Rent | E3: Jan-25 | F3: 8 | G3: None
A4: Tenant C | B4: 50000 | C4: 29 | D4: Net Lease (Stop=0) | E4: Jan-25 | F4: 3 | G4: None
A5: Tenant D | B5: 30000 | C5: 42 | D5: $11.50/sf | E5: Jun-25 | F5: 10 | G5: $50/sf bump in Month 57
B6: =SUM(B2:B5) -> 145000

Sheet Monthly Proforma
A1: Month # | B1: Month/Year | C1: Tenant A Rent | D1: Tenant B Rent | E1: Tenant C Rent | F1: Tenant D Rent | G1: Total Rent | H1: Total Pass-Throughs | I1: PGI | J1: Vacancy | K1: EGI | L1: Expenses | M1: NOI | N1: Capital Reserves | O1: Cash Flow | Q1: Year | R1: Sales per SF | S1: Total Sales | T1: Percentage Rent
A2: 1 | B2: 45682 | C2: =('Tenant Data'!B2*'Tenant Data'!C2)/12 -> 131250 | D2: =(41 * 30000) / 12 + IF((250 * 30000) > 9800000, ((250 * 30000) - 9800000) * 0.1 / 12, 0) -> 102500 | E2: =('Tenant Data'!B4*'Tenant Data'!C4)/12 -> 120833.33 | F2: =IF(A2 >= 57, (50 * 30000) / 12, IF(A2 >= 6, (42 * 30000) / 12, 0)) -> 0 | G2: =SUM(C2:F2) -> 354583.33 | H2: =IF(A2 >= 1, ((15.8 - 10) * 35000 / 12), 0) + IF(A2 <= 36, (15.8 * 50000 / 12), 0) + IF(A2 >= 6, ((15.8 - 11.5) * 30000 / 12), 0) -> 82750 | I2: =G2+H2 -> 437333.33 | J2: =(I2*0.1) -> 43733.333 | K2: =I2-J2 -> 393600 | L2: =(15.8*145000/12)+(0.03*(F2-(0.1*F2))) -> 190916.67 | M2: =(K2-L2) -> 202683.33 | N2: =(0.25*145000/12)*(1+3%)^(INT((A2-1)/12)) -> 3020.8333 | O2: =(M2-N2) -> 199662.5 | Q2: 2025 | R2: 250 | S2: =250 * 30000 -> 7500000 | T2: =IF(7500000 > 9800000, (7500000-9800000)*0.1, 0) -> 0
A3: 2 | B3: 45713 | C3: =(45*35000*(1+0.03)^(INT((A3-1)/12)))/12 -> 131250 | D3: =(41 * 30000) / 12 + IF((250 * 30000) > 9800000, ((250 * 30000) - 9800000) * 0.1 / 12, 0) -> 102500 | E3: =IF(A2<=36, (29 * 50000) / 12, IF(A2<=42, 0, (29 * 50000) / 12)) -> 120833.33 | F3: =IF(A3 >= 57, (50 * 30000) / 12, IF(A3 >= 6, (42 * 30000) / 12, 0)) -> 0 | G3: =SUM(C3:F3) -> 354583.33 | H3: =IF(A3 >= 1, ((15.8 - 10) * 35000 / 12), 0) + IF(A3 <= 36, (15.8 * 50000 / 12), 0) + IF(A3 >= 6, ((15.8 - 11.5) * 30000 / 12), 0) -> 82750 | I3: =G3+H3 -> 437333.33 | J3: =(I3*0.1) -> 43733.333 | K3: =I3-J3 -> 393600 | L3: =(15.8*145000/12)+(0.03*(F3-(0.1*F3))) -> 190916.67 | M3: =(K3-L3) -> 202683.33 | N3: =(0.25*145000/12)*(1+3%)^(INT((A3-1)/12)) -> 3020.8333 | O3: =(M3-N3) -> 199662.5 | Q3: 2026 | R3: 350 | S3: =350 * 30000 -> 10500000 | T3: =IF(10500000 > 9800000, (10500000-9800000)*0.1, 0) -> 70000
A4: 3 | B4: 45741 | C4: =(45*35000*(1+0.03)^(INT((A4-1)/12)))/12 -> 131250 | D4: =(41 * 30000) / 12 + IF((250 * 30000) > 9800000, ((250 * 30000) - 9800000) * 0.1 / 12, 0) -> 102500 | E4: =IF(A3<=36, (29 * 50000) / 12, IF(A3<=42, 0, (29 * 50000) / 12)) -> 120833.33 | F4: =IF(A4 >= 57, (50 * 30000) / 12, IF(A4 >= 6, (42 * 30000) / 12, 0)) -> 0 | G4: =SUM(C4:F4) -> 354583.33 | H4: =IF(A4 >= 1, ((15.8 - 10) * 35000 / 12), 0) + IF(A4 <= 36, (15.8 * 50000 / 12), 0) + IF(A4 >= 6, ((15.8 - 11.5) * 30000 / 12), 0) -> 82750 | I4: =G4+H4 -> 437333.33 | J4: =(I4*0.1) -> 43733.333 | K4: =I4-J4 -> 393600 | L4: =(15.8*145000/12)+(0.03*(F4-(0.1*F4))) -> 190916.67 | M4: =(K4-L4) -> 202683.33 | N4: =(0.25*145000/12)*(1+3%)^(INT((A4-1)/12)) -> 3020.8333 | O4: =(M4-N4) -> 199662.5 | Q4: 2027 | R4: 410 | S4: =410 * 30000 -> 12300000 | T4: =IF(12300000 > 9800000, (12300000-9800000)*0.1, 0) -> 250000
A5: 4 | B5: 45772 | C5: =(45*35000*(1+0.03)^(INT((A5-1)/12)))/12 -> 131250 | D5: =(41 * 30000) / 12 + IF((250 * 30000) > 9800000, ((250 * 30000) - 9800000) * 0.1 / 12, 0) -> 102500 | E5: =IF(A4<=36, (29 * 50000) / 12, IF(A4<=42, 0, (29 * 50000) / 12)) -> 120833.33 | F5: =IF(A5 >= 57, (50 * 30000) / 12, IF(A5 >= 6, (42 * 30000) / 12, 0)) -> 0 | G5: =SUM(C5:F5) -> 354583.33 | H5: =IF(A5 >= 1, ((15.8 - 10) * 35000 / 12), 0) + IF(A5 <= 36, (15.8 * 50000 / 12), 0) + IF(A5 >= 6, ((15.8 - 11.5) * 30000 / 12), 0) -> 82750 | I5: =G5+H5 -> 437333.33 | J5: =(I5*0.1) -> 43733.333 | K5: =I5-J5 -> 393600 | L5: =(15.8*145000/12)+(0.03*(F5-(0.1*F5))) -> 190916.67 | M5: =(K5-L5) -> 202683.33 | N5: =(0.25*145000/12)*(1+3%)^(INT((A5-1)/12)) -> 3020.8333 | O5: =(M5-N5) -> 199662.5 | Q5: 2028 | R5: 265 | S5: =265 * 30000 -> 7950000 | T5: =IF(7950000 > 9800000, (7950000-9800000)*0.1, 0) -> 0
A6: 5 | B6: 45802 | C6: =(45*35000*(1+0.03)^(INT((A6-1)/12)))/12 -> 131250 | D6: =(41 * 30000) / 12 + IF((250 * 30000) > 9800000, ((250 * 30000) - 9800000) * 0.1 / 12, 0) -> 102500 | E6: =IF(A5<=36, (29 * 50000) / 12, IF(A5<=42, 0, (29 * 50000) / 12)) -> 120833.33 | F6: =IF(A6 >= 57, (50 * 30000) / 12, IF(A6 >= 6, (42 * 30000) / 12, 0)) -> 0 | G6: =SUM(C6:F6) -> 354583.33 | H6: =IF(A6 >= 1, ((15.8 - 10) * 35000 / 12), 0) + IF(A6 <= 36, (15.8 * 50000 / 12), 0) + IF(A6 >= 6, ((15.8 - 11.5) * 30000 / 12), 0) -> 82750 | I6: =G6+H6 -> 437333.33 | J6: =(I6*0.1) -> 43733.333 | K6: =I6-J6 -> 393600 | L6: =(15.8*145000/12)+(0.03*(F6-(0.1*F6))) -> 190916.67 | M6: =(K6-L6) -> 202683.33 | N6: =(0.25*145000/12)*(1+3%)^(INT((A6-1)/12)) -> 3020.8333 | O6: =(M6-N6) -> 199662.5 | Q6: 2029 | R6: Weighted (500/550) | S6: =(500 * 30000 * 6/12) + (550 * 30000 * 6/12) -> 15750000 | T6: =IF(S6 > 9800000, (S6-9800000)*0.1, 0) -> 595000
A7: 6 | B7: 45833 | C7: =(45*35000*(1+0.03)^(INT((A7-1)/12)))/12 -> 131250 | D7: =(41 * 30000) / 12 + IF((250 * 30000) > 9800000, ((250 * 30000) - 9800000) * 0.1 / 12, 0) -> 102500 | E7: =IF(A6<=36, (29 * 50000) / 12, IF(A6<=42, 0, (29 * 50000) / 12)) -> 120833.33 | F7: =IF(A7 >= 57, (50 * 30000) / 12, IF(A7 >= 6, (42 * 30000) / 12, 0)) -> 105000 | G7: =SUM(C7:F7) -> 459583.33 | H7: =IF(A7 >= 1, ((15.8 - 10) * 35000 / 12), 0) + IF(A7 <= 36, (15.8 * 50000 / 12), 0) + IF(A7 >= 6, ((15.8 - 11.5) * 30000 / 12), 0) -> 93500 | I7: =G7+H7 -> 553083.33 | J7: =(I7*0.1) -> 55308.333 | K7: =I7-J7 -> 497775 | L7: =(15.8*145000/12)+(0.03*(F7-(0.1*F7))) -> 193751.67 | M7: =(K7-L7) -> 304023.33 | N7: =(0.25*145000/12)*(1+3%)^(INT((A7-1)/12)) -> 3020.8333 | O7: =(M7-N7) -> 301002.5
A8: 7 | B8: 45863 | C8: =(45*35000*(1+0.03)^(INT((A8-1)/12)))/12 -> 131250 | D8: =(41 * 30000) / 12 + IF((250 * 30000) > 9800000, ((250 * 30000) - 9800000) * 0.1 / 12, 0) -> 102500 | E8: =IF(A7<=36, (29 * 50000) / 12, IF(A7<=42, 0, (29 * 50000) / 12)) -> 120833.33 | F8: =IF(A8 >= 57, (50 * 30000) / 12, IF(A8 >= 6, (42 * 30000) / 12, 0)) -> 105000 | G8: =SUM(C8:F8) -> 459583.33 | H8: =IF(A8 >= 1, ((15.8 - 10) * 35000 / 12), 0) + IF(A8 <= 36, (15.8 * 50000 / 12), 0) + IF(A8 >= 6, ((15.8 - 11.5) * 30000 / 12), 0) -> 93500 | I8: =G8+H8 -> 553083.33 | J8: =(I8*0.1) -> 55308.333 | K8: =I8-J8 -> 497775 | L8: =(15.8*145000/12)+(0.03*(F8-(0.1*F8))) -> 193751.67 | M8: =(K8-L8) -> 304023.33 | N8: =(0.25*145000/12)*(1+3%)^(INT((A8-1)/12)) -> 3020.8333 | O8: =(M8-N8) -> 301002.5 | R8: `
A9: 8 | B9: 45894 | C9: =(45*35000*(1+0.03)^(INT((A9-1)/12)))/12 -> 131250 | D9: =(41 * 30000) / 12 + IF((250 * 30000) > 9800000, ((250 * 30000) - 9800000) * 0.1 / 12, 0) -> 102500 | E9: =IF(A8<=36, (29 * 50000) / 12, IF(A8<=42, 0, (29 * 50000) / 12)) -> 120833.33 | F9: =IF(A9 >= 57, (50 * 30000) / 12, IF(A9 >= 6, (42 * 30000) / 12, 0)) -> 105000 | G9: =SUM(C9:F9) -> 459583.33 | H9: =IF(A9 >= 1, ((15.8 - 10) * 35000 / 12), 0) + IF(A9 <= 36, (15.8 * 50000 / 12), 0) + IF(A9 >= 6, ((15.8 - 11.5) * 30000 / 12), 0) -> 93500 | I9: =G9+H9 -> 553083.33 | J9: =(I9*0.1) -> 55308.333 | K9: =I9-J9 -> 497775 | L9: =(15.8*145000/12)+(0.03*(F9-(0.1*F9))) -> 193751.67 | M9: =(K9-L9) -> 304023.33 | N9: =(0.25*145000/12)*(1+3%)^(INT((A9-1)/12)) -> 3020.8333 | O9: =(M9-N9) -> 301002.5
A10: 9 | B10: 45925 | C10: =(45*35000*(1+0.03)^(INT((A10-1)/12)))/12 -> 131250 | D10: =(41 * 30000) / 12 + IF((250 * 30000) > 9800000, ((250 * 30000) - 9800000) * 0.1 / 12, 0) -> 102500 | E10: =IF(A9<=36, (29 * 50000) / 12, IF(A9<=42, 0, (29 * 50000) / 12)) -> 120833.33 | F10: =IF(A10 >= 57, (50 * 30000) / 12, IF(A10 >= 6, (42 * 30000) / 12, 0)) -> 105000 | G10: =SUM(C10:F10) -> 459583.33 | H10: =IF(A10 >= 1, ((15.8 - 10) * 35000 / 12), 0) + IF(A10 <= 36, (15.8 * 50000 / 12), 0) + IF(A10 >= 6, ((15.8 - 11.5) * 30000 / 12), 0) -> 93500 | I10: =G10+H10 -> 553083.33 | J10: =(I10*0.1) -> 55308.333 | K10: =I10-J10 -> 497775 | L10: =(15.8*145000/12)+(0.03*(F10-(0.1*F10))) -> 193751.67 | M10: =(K10-L10) -> 304023.33 | N10: =(0.25*145000/12)*(1+3%)^(INT((A10-1)/12)) -> 3020.8333 | O10: =(M10-N10) -> 301002.5 | AF10: `
A11: 10 | B11: 45955 | C11: =(45*35000*(1+0.03)^(INT((A11-1)/12)))/12 -> 131250 | D11: =(41 * 30000) / 12 + IF((250 * 30000) > 9800000, ((250 * 30000) - 9800000) * 0.1 / 12, 0) -> 102500 | E11: =IF(A10<=36, (29 * 50000) / 12, IF(A10<=42, 0, (29 * 50000) / 12)) -> 120833.33 | F11: =IF(A11 >= 57, (50 * 30000) / 12, IF(A11 >= 6, (42 * 30000) / 12, 0)) -> 105000 | G11: =SUM(C11:F11) -> 459583.33 | H11: =IF(A11 >= 1, ((15.8 - 10) * 35000 / 12), 0) + IF(A11 <= 36, (15.8 * 50000 / 12), 0) + IF(A11 >= 6, ((15.8 - 11.5) * 30000 / 12), 0) -> 93500 | I11: =G11+H11 -> 553083.33 | J11: =(I11*0.1) -> 55308.333 | K11: =I11-J11 -> 497775 | L11: =(15.8*145000/12)+(0.03*(F11-(0.1*F11))) -> 193751.67 | M11: =(K11-L11) -> 304023.33 | N11: =(0.25*145000/12)*(1+3%)^(INT((A11-1)/12)) -> 3020.8333 | O11: =(M11-N11) -> 301002.5
A12: 11 | B12: 45986 | C12: =(45*35000*(1+0.03)^(INT((A12-1)/12)))/12 -> 131250 | D12: =(41 * 30000) / 12 + IF((250 * 30000) > 9800000, ((250 * 30000) - 9800000) * 0.1 / 12, 0) -> 102500 | E12: =IF(A11<=36, (29 * 50000) / 12, IF(A11<=42, 0, (29 * 50000) / 12)) -> 120833.33 | F12: =IF(A12 >= 57, (50 * 30000) / 12, IF(A12 >= 6, (42 * 30000) / 12, 0)) -> 105000 | G12: =SUM(C12:F12) -> 459583.33 | H12: =IF(A12 >= 1, ((15.8 - 10) * 35000 / 12), 0) + IF(A12 <= 36, (15.8 * 50000 / 12), 0) + IF(A12 >= 6, ((15.8 - 11.5) * 30000 / 12), 0) -> 93500 | I12: =G12+H12 -> 553083.33 | J12: =(I12*0.1) -> 55308.333 | K12: =I12-J12 -> 497775 | L12: =(15.8*145000/12)+(0.03*(F12-(0.1*F12))) -> 193751.67 | M12: =(K12-L12) -> 304023.33 | N12: =(0.25*145000/12)*(1+3%)^(INT((A12-1)/12)) -> 3020.8333 | O12: =(M12-N12) -> 301002.5
A13: 12 | B13: 46016 | C13: =(45*35000*(1+0.03)^(INT((A13-1)/12)))/12 -> 131250 | D13: =(41 * 30000) / 12 + IF((250 * 30000) > 9800000, ((250 * 30000) - 9800000) * 0.1 / 12, 0) -> 102500 | E13: =IF(A12<=36, (29 * 50000) / 12, IF(A12<=42, 0, (29 * 50000) / 12)) -> 120833.33 | F13: =IF(A13 >= 57, (50 * 30000) / 12, IF(A13 >= 6, (42 * 30000) / 12, 0)) -> 105000 | G13: =SUM(C13:F13) -> 459583.33 | H13: =IF(A13 >= 1, ((15.8 - 10) * 35000 / 12), 0) + IF(A13 <= 36, (15.8 * 50000 / 12), 0) + IF(A13 >= 6, ((15.8 - 11.5) * 30000 / 12), 0) -> 93500 | I13: =G13+H13 -> 553083.33 | J13: =(I13*0.1) -> 55308.333 | K13: =I13-J13 -> 497775 | L13: =(15.8*145000/12)+(0.03*(F13-(0.1*F13))) -> 193751.67 | M13: =(K13-L13) -> 304023.33 | N13: =(0.25*145000/12)*(1+3%)^(INT((A13-1)/12)) -> 3020.8333 | O13: =(M13-N13) -> 301002.5
A14: 13 | B14: 46047 | C14: =(45*35000*(1+0.03)^(INT((A14-1)/12)))/12 -> 135187.5 | D14: =(41 * 30000) / 12 + IF((350 * 30000) > 9800000, ((350 * 30000) - 9800000) * 0.1 / 12, 0) -> 108333.33 | E14: =IF(A13<=36, (29 * 50000) / 12, IF(A13<=42, 0, (29 * 50000) / 12)) -> 120833.33 | F14: =IF(A14 >= 57, (50 * 30000) / 12, IF(A14 >= 6, (42 * 30000) / 12, 0)) -> 105000 | G14: =SUM(C14:F14) -> 469354.17 | H14: =IF(A14 >= 1, ((15.8 - 10) * 35000 / 12), 0) + IF(A14 <= 36, (15.8 * 50000 / 12), 0) + IF(A14 >= 6, ((15.8 - 11.5) * 30000 / 12), 0) -> 93500 | I14: =G14+H14 -> 562854.17 | J14: =(I14*0.1) -> 56285.417 | K14: =I14-J14 -> 506568.75 | L14: =(15.8*145000/12)+(0.03*(F14-(0.1*F14))) -> 193751.67 | M14: =(K14-L14) -> 312817.08 | N14: =(0.25*145000/12)*(1+3%)^(INT((A14-1)/12)) -> 3111.4583 | O14: =(M14-N14) -> 309705.62
A15: 14 | B15: 46078 | C15: =(45*35000*(1+0.03)^(INT((A15-1)/12)))/12 -> 135187.5 | D15: =(41 * 30000) / 12 + IF((350 * 30000) > 9800000, ((350 * 30000) - 9800000) * 0.1 / 12, 0) -> 108333.33 | E15: =IF(A14<=36, (29 * 50000) / 12, IF(A14<=42, 0, (29 * 50000) / 12)) -> 120833.33 | F15: =IF(A15 >= 57, (50 * 30000) / 12, IF(A15 >= 6, (42 * 30000) / 12, 0)) -> 105000 | G15: =SUM(C15:F15) -> 469354.17 | H15: =IF(A15 >= 1, ((15.8 - 10) * 35000 / 12), 0) + IF(A15 <= 36, (15.8 * 50000 / 12), 0) + IF(A15 >= 6, ((15.8 - 11.5) * 30000 / 12), 0) -> 93500 | I15: =G15+H15 -> 562854.17 | J15: =(I15*0.1) -> 56285.417 | K15: =I15-J15 -> 506568.75 | L15: =(15.8*145000/12)+(0.03*(F15-(0.1*F15))) -> 193751.67 | M15: =(K15-L15) -> 312817.08 | N15: =(0.25*145000/12)*(1+3%)^(INT((A15-1)/12)) -> 3111.4583 | O15: =(M15-N15) -> 309705.62
A16: 15 | B16: 46106 | C16: =(45*35000*(1+0.03)^(INT((A16-1)/12)))/12 -> 135187.5 | D16: =(41 * 30000) / 12 + IF((350 * 30000) > 9800000, ((350 * 30000) - 9800000) * 0.1 / 12, 0) -> 108333.33 | E16: =IF(A15<=36, (29 * 50000) / 12, IF(A15<=42, 0, (29 * 50000) / 12)) -> 120833.33 | F16: =IF(A16 >= 57, (50 * 30000) / 12, IF(A16 >= 6, (42 * 30000) / 12, 0)) -> 105000 | G16: =SUM(C16:F16) -> 469354.17 | H16: =IF(A16 >= 1, ((15.8 - 10) * 35000 / 12), 0) + IF(A16 <= 36, (15.8 * 50000 / 12), 0) + IF(A16 >= 6, ((15.8 - 11.5) * 30000 / 12), 0) -> 93500 | I16: =G16+H16 -> 562854.17 | J16: =(I16*0.1) -> 56285.417 | K16: =I16-J16 -> 506568.75 | L16: =(15.8*145000/12)+(0.03*(F16-(0.1*F16))) -> 193751.67 | M16: =(K16-L16) -> 312817.08 | N16: =(0.25*145000/12)*(1+3%)^(INT((A16-1)/12)) -> 3111.4583 | O16: =(M16-N16) -> 309705.62
A17: 16 | B17: 46137 | C17: =(45*35000*(1+0.03)^(INT((A17-1)/12)))/12 -> 135187.5 | D17: =(41 * 30000) / 12 + IF((350 * 30000) > 9800000, ((350 * 30000) - 9800000) * 0.1 / 12, 0) -> 108333.33 | E17: =IF(A16<=36, (29 * 50000) / 12, IF(A16<=42, 0, (29 * 50000) / 12)) -> 120833.33 | F17: =IF(A17 >= 57, (50 * 30000) / 12, IF(A17 >= 6, (42 * 30000) / 12, 0)) -> 105000 | G17: =SUM(C17:F17) -> 469354.17 | H17: =IF(A17 >= 1, ((15.8 - 10) * 35000 / 12), 0) + IF(A17 <= 36, (15.8 * 50000 / 12), 0) + IF(A17 >= 6, ((15.8 - 11.5) * 30000 / 12), 0) -> 93500 | I17: =G17+H17 -> 562854.17 | J17: =(I17*0.1) -> 56285.417 | K17: =I17-J17 -> 506568.75 | L17: =(15.8*145000/12)+(0.03*(F17-(0.1*F17))) -> 193751.67 | M17: =(K17-L17) -> 312817.08 | N17: =(0.25*145000/12)*(1+3%)^(INT((A17-1)/12)) -> 3111.4583 | O17: =(M17-N17) -> 309705.62
A18: 17 | B18: 46167 | C18: =(45*35000*(1+0.03)^(INT((A18-1)/12)))/12 -> 135187.5 | D18: =(41 * 30000) / 12 + IF((350 * 30000) > 9800000, ((350 * 30000) - 9800000) * 0.1 / 12, 0) -> 108333.33 | E18: =IF(A17<=36, (29 * 50000) / 12, IF(A17<=42, 0, (29 * 50000) / 12)) -> 120833.33 | F18: =IF(A18 >= 57, (50 * 30000) / 12, IF(A18 >= 6, (42 * 30000) / 12, 0)) -> 105000 | G18: =SUM(C18:F18) -> 469354.17 | H18: =IF(A18 >= 1, ((15.8 - 10) * 35000 / 12), 0) + IF(A18 <= 36, (15.8 * 50000 / 12), 0) + IF(A18 >= 6, ((15.8 - 11.5) * 30000 / 12), 0) -> 93500 | I18: =G18+H18 -> 562854.17 | J18: =(I18*0.1) -> 56285.417 | K18: =I18-J18 -> 506568.75 | L18: =(15.8*145000/12)+(0.03*(F18-(0.1*F18))) -> 193751.67 | M18: =(K18-L18) -> 312817.08 | N18: =(0.25*145000/12)*(1+3%)^(INT((A18-1)/12)) -> 3111.4583 | O18: =(M18-N18) -> 309705.62
A19: 18 | B19: 46198 | C19: =(45*35000*(1+0.03)^(INT((A19-1)/12)))/12 -> 135187.5 | D19: =(41 * 30000) / 12 + IF((350 * 30000) > 9800000, ((350 * 30000) - 9800000) * 0.1 / 12, 0) -> 108333.33 | E19: =IF(A18<=36, (29 * 50000) / 12, IF(A18<=42, 0, (29 * 50000) / 12)) -> 120833.33 | F19: =IF(A19 >= 57, (50 * 30000) / 12, IF(A19 >= 6, (42 * 30000) / 12, 0)) -> 105000 | G19: =SUM(C19:F19) -> 469354.17 | H19: =IF(A19 >= 1, ((15.8 - 10) * 35000 / 12), 0) + IF(A19 <= 36, (15.8 * 50000 / 12), 0) + IF(A19 >= 6, ((15.8 - 11.5) * 30000 / 12), 0) -> 93500 | I19: =G19+H19 -> 562854.17 | J19: =(I19*0.1) -> 56285.417 | K19: =I19-J19 -> 506568.75 | L19: =(15.8*145000/12)+(0.03*(F19-(0.1*F19))) -> 193751.67 | M19: =(K19-L19) -> 312817.08 | N19: =(0.25*145000/12)*(1+3%)^(INT((A19-1)/12)) -> 3111.4583 | O19: =(M19-N19) -> 309705.62
A20: 19 | B20: 46228 | C20: =(45*35000*(1+0.03)^(INT((A20-1)/12)))/12 -> 135187.5 | D20: =(41 * 30000) / 12 + IF((350 * 30000) > 9800000, ((350 * 30000) - 9800000) * 0.1 / 12, 0) -> 108333.33 | E20: =IF(A19<=36, (29 * 50000) / 12, IF(A19<=42, 0, (29 * 50000) / 12)) -> 120833.33 | F20: =IF(A20 >= 57, (50 * 30000) / 12, IF(A20 >= 6, (42 * 30000) / 12, 0)) -> 105000 | G20: =SUM(C20:F20) -> 469354.17 | H20: =IF(A20 >= 1, ((15.8 - 10) * 35000 / 12), 0) + IF(A20 <= 36, (15.8 * 50000 / 12), 0) + IF(A20 >= 6, ((15.8 - 11.5) * 30000 / 12), 0) -> 93500 | I20: =G20+H20 -> 562854.17 | J20: =(I20*0.1) -> 56285.417 | K20: =I20-J20 -> 506568.75 | L20: =(15.8*145000/12)+(0.03*(F20-(0.1*F20))) -> 193751.67 | M20: =(K20-L20) -> 312817.08 | N20: =(0.25*145000/12)*(1+3%)^(INT((A20-1)/12)) -> 3111.4583 | O20: =(M20-N20) -> 309705.62
A21: 20 | B21: 46259 | C21: =(45*35000*(1+0.03)^(INT((A21-1)/12)))/12 -> 135187.5 | D21: =(41 * 30000) / 12 + IF((350 * 30000) > 9800000, ((350 * 30000) - 9800000) * 0.1 / 12, 0) -> 108333.33 | E21: =IF(A20<=36, (29 * 50000) / 12, IF(A20<=42, 0, (29 * 50000) / 12)) -> 120833.33 | F21: =IF(A21 >= 57, (50 * 30000) / 12, IF(A21 >= 6, (42 * 30000) / 12, 0)) -> 105000 | G21: =SUM(C21:F21) -> 469354.17 | H21: =IF(A21 >= 1, ((15.8 - 10) * 35000 / 12), 0) + IF(A21 <= 36, (15.8 * 50000 / 12), 0) + IF(A21 >= 6, ((15.8 - 11.5) * 30000 / 12), 0) -> 93500 | I21: =G21+H21 -> 562854.17 | J21: =(I21*0.1) -> 56285.417 | K21: =I21-J21 -> 506568.75 | L21: =(15.8*145000/12)+(0.03*(F21-(0.1*F21))) -> 193751.67 | M21: =(K21-L21) -> 312817.08 | N21: =(0.25*145000/12)*(1+3%)^(INT((A21-1)/12)) -> 3111.4583 | O21: =(M21-N21) -> 309705.62
A22: 21 | B22: 46290 | C22: =(45*35000*(1+0.03)^(INT((A22-1)/12)))/12 -> 135187.5 | D22: =(41 * 30000) / 12 + IF((350 * 30000) > 9800000, ((350 * 30000) - 9800000) * 0.1 / 12, 0) -> 108333.33 | E22: =IF(A21<=36, (29 * 50000) / 12, IF(A21<=42, 0, (29 * 50000) / 12)) -> 120833.33 | F22: =IF(A22 >= 57, (50 * 30000) / 12, IF(A22 >= 6, (42 * 30000) / 12, 0)) -> 105000 | G22: =SUM(C22:F22) -> 469354.17 | H22: =IF(A22 >= 1, ((15.8 - 10) * 35000 / 12), 0) + IF(A22 <= 36, (15.8 * 50000 / 12), 0) + IF(A22 >= 6, ((15.8 - 11.5) * 30000 / 12), 0) -> 93500 | I22: =G22+H22 -> 562854.17 | J22: =(I22*0.1) -> 56285.417 | K22: =I22-J22 -> 506568.75 | L22: =(15.8*145000/12)+(0.03*(F22-(0.1*F22))) -> 193751.67 | M22: =(K22-L22) -> 312817.08 | N22: =(0.25*145000/12)*(1+3%)^(INT((A22-1)/12)) -> 3111.4583 | O22: =(M22-N22) -> 309705.62
A23: 22 | B23: 46320 | C23: =(45*35000*(1+0.03)^(INT((A23-1)/12)))/12 -> 135187.5 | D23: =(41 * 30000) / 12 + IF((350 * 30000) > 9800000, ((350 * 30000) - 9800000) * 0.1 / 12, 0) -> 108333.33 | E23: =IF(A22<=36, (29 * 50000) / 12, IF(A22<=42, 0, (29 * 50000) / 12)) -> 120833.33 | F23: =IF(A23 >= 57, (50 * 30000) / 12, IF(A23 >= 6, (42 * 30000) / 12, 0)) -> 105000 | G23: =SUM(C23:F23) -> 469354.17 | H23: =IF(A23 >= 1, ((15.8 - 10) * 35000 / 12), 0) + IF(A23 <= 36, (15.8 * 50000 / 12), 0) + IF(A23 >= 6, ((15.8 - 11.5) * 30000 / 12), 0) -> 93500 | I23: =G23+H23 -> 562854.17 | J23: =(I23*0.1) -> 56285.417 | K23: =I23-J23 -> 506568.75 | L23: =(15.8*145000/12)+(0.03*(F23-(0.1*F23))) -> 193751.67 | M23: =(K23-L23) -> 312817.08 | N23: =(0.25*145000/12)*(1+3%)^(INT((A23-1)/12)) -> 3111.4583 | O23: =(M23-N23) -> 309705.62
A24: 23 | B24: 46351 | C24: =(45*35000*(1+0.03)^(INT((A24-1)/12)))/12 -> 135187.5 | D24: =(41 * 30000) / 12 + IF((350 * 30000) > 9800000, ((350 * 30000) - 9800000) * 0.1 / 12, 0) -> 108333.33 | E24: =IF(A23<=36, (29 * 50000) / 12, IF(A23<=42, 0, (29 * 50000) / 12)) -> 120833.33 | F24: =IF(A24 >= 57, (50 * 30000) / 12, IF(A24 >= 6, (42 * 30000) / 12, 0)) -> 105000 | G24: =SUM(C24:F24) -> 469354.17 | H24: =IF(A24 >= 1, ((15.8 - 10) * 35000 / 12), 0) + IF(A24 <= 36, (15.8 * 50000 / 12), 0) + IF(A24 >= 6, ((15.8 - 11.5) * 30000 / 12), 0) -> 93500 | I24: =G24+H24 -> 562854.17 | J24: =(I24*0.1) -> 56285.417 | K24: =I24-J24 -> 506568.75 | L24: =(15.8*145000/12)+(0.03*(F24-(0.1*F24))) -> 193751.67 | M24: =(K24-L24) -> 312817.08 | N24: =(0.25*145000/12)*(1+3%)^(INT((A24-1)/12)) -> 3111.4583 | O24: =(M24-N24) -> 309705.62
A25: 24 | B25: 46381 | C25: =(45*35000*(1+0.03)^(INT((A25-1)/12)))/12 -> 135187.5 | D25: =(41 * 30000) / 12 + IF((350 * 30000) > 9800000, ((350 * 30000) - 9800000) * 0.1 / 12, 0) -> 108333.33 | E25: =IF(A24<=36, (29 * 50000) / 12, IF(A24<=42, 0, (29 * 50000) / 12)) -> 120833.33 | F25: =IF(A25 >= 57, (50 * 30000) / 12, IF(A25 >= 6, (42 * 30000) / 12, 0)) -> 105000 | G25: =SUM(C25:F25) -> 469354.17 | H25: =IF(A25 >= 1, ((15.8 - 10) * 35000 / 12), 0) + IF(A25 <= 36, (15.8 * 50000 / 12), 0) + IF(A25 >= 6, ((15.8 - 11.5) * 30000 / 12), 0) -> 93500 | I25: =G25+H25 -> 562854.17 | J25: =(I25*0.1) -> 56285.417 | K25: =I25-J25 -> 506568.75 | L25: =(15.8*145000/12)+(0.03*(F25-(0.1*F25))) -> 193751.67 | M25: =(K25-L25) -> 312817.08 | N25: =(0.25*145000/12)*(1+3%)^(INT((A25-1)/12)) -> 3111.4583 | O25: =(M25-N25) -> 309705.62
A26: 25 | B26: 46412 | C26: =(45*35000*(1+0.03)^(INT((A26-1)/12)))/12 -> 139243.12 | D26: =(41 * 30000) / 12 + IF((410 * 30000) > 9800000, ((410 * 30000) - 9800000) * 0.1 / 12, 0) -> 123333.33 | E26: =IF(A25<=36, (29 * 50000) / 12, IF(A25<=42, 0, (29 * 50000) / 12)) -> 120833.33 | F26: =IF(A26 >= 57, (50 * 30000) / 12, IF(A26 >= 6, (42 * 30000) / 12, 0)) -> 105000 | G26: =SUM(C26:F26) -> 488409.79 | H26: =IF(A26 >= 1, ((15.8 - 10) * 35000 / 12), 0) + IF(A26 <= 36, (15.8 * 50000 / 12), 0) + IF(A26 >= 6, ((15.8 - 11.5) * 30000 / 12), 0) -> 93500 | I26: =G26+H26 -> 581909.79 | J26: =(I26*0.1) -> 58190.979 | K26: =I26-J26 -> 523718.81 | L26: =(15.8*145000/12)+(0.03*(F26-(0.1*F26))) -> 193751.67 | M26: =(K26-L26) -> 329967.15 | N26: =(0.25*145000/12)*(1+3%)^(INT((A26-1)/12)) -> 3204.8021 | O26: =(M26-N26) -> 326762.34
A27: 26 | B27: 46443 | C27: =(45*35000*(1+0.03)^(INT((A27-1)/12)))/12 -> 139243.12 | D27: =(41 * 30000) / 12 + IF((410 * 30000) > 9800000, ((410 * 30000) - 9800000) * 0.1 / 12, 0) -> 123333.33 | E27: =IF(A26<=36, (29 * 50000) / 12, IF(A26<=42, 0, (29 * 50000) / 12)) -> 120833.33 | F27: =IF(A27 >= 57, (50 * 30000) / 12, IF(A27 >= 6, (42 * 30000) / 12, 0)) -> 105000 | G27: =SUM(C27:F27) -> 488409.79 | H27: =IF(A27 >= 1, ((15.8 - 10) * 35000 / 12), 0) + IF(A27 <= 36, (15.8 * 50000 / 12), 0) + IF(A27 >= 6, ((15.8 - 11.5) * 30000 / 12), 0) -> 93500 | I27: =G27+H27 -> 581909.79 | J27: =(I27*0.1) -> 58190.979 | K27: =I27-J27 -> 523718.81 | L27: =(15.8*145000/12)+(0.03*(F27-(0.1*F27))) -> 193751.67 | M27: =(K27-L27) -> 329967.15 | N27: =(0.25*145000/12)*(1+3%)^(INT((A27-1)/12)) -> 3204.8021 | O27: =(M27-N27) -> 326762.34
A28: 27 | B28: 46471 | C28: =(45*35000*(1+0.03)^(INT((A28-1)/12)))/12 -> 139243.12 | D28: =(41 * 30000) / 12 + IF((410 * 30000) > 9800000, ((410 * 30000) - 9800000) * 0.1 / 12, 0) -> 123333.33 | E28: =IF(A27<=36, (29 * 50000) / 12, IF(A27<=42, 0, (29 * 50000) / 12)) -> 120833.33 | F28: =IF(A28 >= 57, (50 * 30000) / 12, IF(A28 >= 6, (42 * 30000) / 12, 0)) -> 105000 | G28: =SUM(C28:F28) -> 488409.79 | H28: =IF(A28 >= 1, ((15.8 - 10) * 35000 / 12), 0) + IF(A28 <= 36, (15.8 * 50000 / 12), 0) + IF(A28 >= 6, ((15.8 - 11.5) * 30000 / 12), 0) -> 93500 | I28: =G28+H28 -> 581909.79 | J28: =(I28*0.1) -> 58190.979 | K28: =I28-J28 -> 523718.81 | L28: =(15.8*145000/12)+(0.03*(F28-(0.1*F28))) -> 193751.67 | M28: =(K28-L28) -> 329967.15 | N28: =(0.25*145000/12)*(1+3%)^(INT((A28-1)/12)) -> 3204.8021 | O28: =(M28-N28) -> 326762.34
A29: 28 | B29: 46502 | C29: =(45*35000*(1+0.03)^(INT((A29-1)/12)))/12 -> 139243.12 | D29: =(41 * 30000) / 12 + IF((410 * 30000) > 9800000, ((410 * 30000) - 9800000) * 0.1 / 12, 0) -> 123333.33 | E29: =IF(A28<=36, (29 * 50000) / 12, IF(A28<=42, 0, (29 * 50000) / 12)) -> 120833.33 | F29: =IF(A29 >= 57, (50 * 30000) / 12, IF(A29 >= 6, (42 * 30000) / 12, 0)) -> 105000 | G29: =SUM(C29:F29) -> 488409.79 | H29: =IF(A29 >= 1, ((15.8 - 10) * 35000 / 12), 0) + IF(A29 <= 36, (15.8 * 50000 / 12), 0) + IF(A29 >= 6, ((15.8 - 11.5) * 30000 / 12), 0) -> 93500 | I29: =G29+H29 -> 581909.79 | J29: =(I29*0.1) -> 58190.979 | K29: =I29-J29 -> 523718.81 | L29: =(15.8*145000/12)+(0.03*(F29-(0.1*F29))) -> 193751.67 | M29: =(K29-L29) -> 329967.15 | N29: =(0.25*145000/12)*(1+3%)^(INT((A29-1)/12)) -> 3204.8021 | O29: =(M29-N29) -> 326762.34
A30: 29 | B30: 46532 | C30: =(45*35000*(1+0.03)^(INT((A30-1)/12)))/12 -> 139243.12 | D30: =(41 * 30000) / 12 + IF((410 * 30000) > 9800000, ((410 * 30000) - 9800000) * 0.1 / 12, 0) -> 123333.33 | E30: =IF(A29<=36, (29 * 50000) / 12, IF(A29<=42, 0, (29 * 50000) / 12)) -> 120833.33 | F30: =IF(A30 >= 57, (50 * 30000) / 12, IF(A30 >= 6, (42 * 30000) / 12, 0)) -> 105000 | G30: =SUM(C30:F30) -> 488409.79 | H30: =IF(A30 >= 1, ((15.8 - 10) * 35000 / 12), 0) + IF(A30 <= 36, (15.8 * 50000 / 12), 0) + IF(A30 >= 6, ((15.8 - 11.5) * 30000 / 12), 0) -> 93500 | I30: =G30+H30 -> 581909.79 | J30: =(I30*0.1) -> 58190.979 | K30: =I30-J30 -> 523718.81 | L30: =(15.8*145000/12)+(0.03*(F30-(0.1*F30))) -> 193751.67 | M30: =(K30-L30) -> 329967.15 | N30: =(0.25*145000/12)*(1+3%)^(INT((A30-1)/12)) -> 3204.8021 | O30: =(M30-N30) -> 326762.34
A31: 30 | B31: 46563 | C31: =(45*35000*(1+0.03)^(INT((A31-1)/12)))/12 -> 139243.12 | D31: =(41 * 30000) / 12 + IF((410 * 30000) > 9800000, ((410 * 30000) - 9800000) * 0.1 / 12, 0) -> 123333.33 | E31: =IF(A30<=36, (29 * 50000) / 12, IF(A30<=42, 0, (29 * 50000) / 12)) -> 120833.33 | F31: =IF(A31 >= 57, (50 * 30000) / 12, IF(A31 >= 6, (42 * 30000) / 12, 0)) -> 105000 | G31: =SUM(C31:F31) -> 488409.79 | H31: =IF(A31 >= 1, ((15.8 - 10) * 35000 / 12), 0) + IF(A31 <= 36, (15.8 * 50000 / 12), 0) + IF(A31 >= 6, ((15.8 - 11.5) * 30000 / 12), 0) -> 93500 | I31: =G31+H31 -> 581909.79 | J31: =(I31*0.1) -> 58190.979 | K31: =I31-J31 -> 523718.81 | L31: =(15.8*145000/12)+(0.03*(F31-(0.1*F31))) -> 193751.67 | M31: =(K31-L31) -> 329967.15 | N31: =(0.25*145000/12)*(1+3%)^(INT((A31-1)/12)) -> 3204.8021 | O31: =(M31-N31) -> 326762.34
A32: 31 | B32: 46593 | C32: =(45*35000*(1+0.03)^(INT((A32-1)/12)))/12 -> 139243.12 | D32: =(41 * 30000) / 12 + IF((410 * 30000) > 9800000, ((410 * 30000) - 9800000) * 0.1 / 12, 0) -> 123333.33 | E32: =IF(A31<=36, (29 * 50000) / 12, IF(A31<=42, 0, (29 * 50000) / 12)) -> 120833.33 | F32: =IF(A32 >= 57, (50 * 30000) / 12, IF(A32 >= 6, (42 * 30000) / 12, 0)) -> 105000 | G32: =SUM(C32:F32) -> 488409.79 | H32: =IF(A32 >= 1, ((15.8 - 10) * 35000 / 12), 0) + IF(A32 <= 36, (15.8 * 50000 / 12), 0) + IF(A32 >= 6, ((15.8 - 11.5) * 30000 / 12), 0) -> 93500 | I32: =G32+H32 -> 581909.79 | J32: =(I32*0.1) -> 58190.979 | K32: =I32-J32 -> 523718.81 | L32: =(15.8*145000/12)+(0.03*(F32-(0.1*F32))) -> 193751.67 | M32: =(K32-L32) -> 329967.15 | N32: =(0.25*145000/12)*(1+3%)^(INT((A32-1)/12)) -> 3204.8021 | O32: =(M32-N32) -> 326762.34
A33: 32 | B33: 46624 | C33: =(45*35000*(1+0.03)^(INT((A33-1)/12)))/12 -> 139243.12 | D33: =(41 * 30000) / 12 + IF((410 * 30000) > 9800000, ((410 * 30000) - 9800000) * 0.1 / 12, 0) -> 123333.33 | E33: =IF(A32<=36, (29 * 50000) / 12, IF(A32<=42, 0, (29 * 50000) / 12)) -> 120833.33 | F33: =IF(A33 >= 57, (50 * 30000) / 12, IF(A33 >= 6, (42 * 30000) / 12, 0)) -> 105000 | G33: =SUM(C33:F33) -> 488409.79 | H33: =IF(A33 >= 1, ((15.8 - 10) * 35000 / 12), 0) + IF(A33 <= 36, (15.8 * 50000 / 12), 0) + IF(A33 >= 6, ((15.8 - 11.5) * 30000 / 12), 0) -> 93500 | I33: =G33+H33 -> 581909.79 | J33: =(I33*0.1) -> 58190.979 | K33: =I33-J33 -> 523718.81 | L33: =(15.8*145000/12)+(0.03*(F33-(0.1*F33))) -> 193751.67 | M33: =(K33-L33) -> 329967.15 | N33: =(0.25*145000/12)*(1+3%)^(INT((A33-1)/12)) -> 3204.8021 | O33: =(M33-N33) -> 326762.34
A34: 33 | B34: 46655 | C34: =(45*35000*(1+0.03)^(INT((A34-1)/12)))/12 -> 139243.12 | D34: =(41 * 30000) / 12 + IF((410 * 30000) > 9800000, ((410 * 30000) - 9800000) * 0.1 / 12, 0) -> 123333.33 | E34: =IF(A33<=36, (29 * 50000) / 12, IF(A33<=42, 0, (29 * 50000) / 12)) -> 120833.33 | F34: =IF(A34 >= 57, (50 * 30000) / 12, IF(A34 >= 6, (42 * 30000) / 12, 0)) -> 105000 | G34: =SUM(C34:F34) -> 488409.79 | H34: =IF(A34 >= 1, ((15.8 - 10) * 35000 / 12), 0) + IF(A34 <= 36, (15.8 * 50000 / 12), 0) + IF(A34 >= 6, ((15.8 - 11.5) * 30000 / 12), 0) -> 93500 | I34: =G34+H34 -> 581909.79 | J34: =(I34*0.1) -> 58190.979 | K34: =I34-J34 -> 523718.81 | L34: =(15.8*145000/12)+(0.03*(F34-(0.1*F34))) -> 193751.67 | M34: =(K34-L34) -> 329967.15 | N34: =(0.25*145000/12)*(1+3%)^(INT((A34-1)/12)) -> 3204.8021 | O34: =(M34-N34) -> 326762.34
A35: 34 | B35: 46685 | C35: =(45*35000*(1+0.03)^(INT((A35-1)/12)))/12 -> 139243.12 | D35: =(41 * 30000) / 12 + IF((410 * 30000) > 9800000, ((410 * 30000) - 9800000) * 0.1 / 12, 0) -> 123333.33 | E35: =IF(A34<=36, (29 * 50000) / 12, IF(A34<=42, 0, (29 * 50000) / 12)) -> 120833.33 | F35: =IF(A35 >= 57, (50 * 30000) / 12, IF(A35 >= 6, (42 * 30000) / 12, 0)) -> 105000 | G35: =SUM(C35:F35) -> 488409.79 | H35: =IF(A35 >= 1, ((15.8 - 10) * 35000 / 12), 0) + IF(A35 <= 36, (15.8 * 50000 / 12), 0) + IF(A35 >= 6, ((15.8 - 11.5) * 30000 / 12), 0) -> 93500 | I35: =G35+H35 -> 581909.79 | J35: =(I35*0.1) -> 58190.979 | K35: =I35-J35 -> 523718.81 | L35: =(15.8*145000/12)+(0.03*(F35-(0.1*F35))) -> 193751.67 | M35: =(K35-L35) -> 329967.15 | N35: =(0.25*145000/12)*(1+3%)^(INT((A35-1)/12)) -> 3204.8021 | O35: =(M35-N35) -> 326762.34
A36: 35 | B36: 46716 | C36: =(45*35000*(1+0.03)^(INT((A36-1)/12)))/12 -> 139243.12 | D36: =(41 * 30000) / 12 + IF((410 * 30000) > 9800000, ((410 * 30000) - 9800000) * 0.1 / 12, 0) -> 123333.33 | E36: =IF(A35<=36, (29 * 50000) / 12, IF(A35<=42, 0, (29 * 50000) / 12)) -> 120833.33 | F36: =IF(A36 >= 57, (50 * 30000) / 12, IF(A36 >= 6, (42 * 30000) / 12, 0)) -> 105000 | G36: =SUM(C36:F36) -> 488409.79 | H36: =IF(A36 >= 1, ((15.8 - 10) * 35000 / 12), 0) + IF(A36 <= 36, (15.8 * 50000 / 12), 0) + IF(A36 >= 6, ((15.8 - 11.5) * 30000 / 12), 0) -> 93500 | I36: =G36+H36 -> 581909.79 | J36: =(I36*0.1) -> 58190.979 | K36: =I36-J36 -> 523718.81 | L36: =(15.8*145000/12)+(0.03*(F36-(0.1*F36))) -> 193751.67 | M36: =(K36-L36) -> 329967.15 | N36: =(0.25*145000/12)*(1+3%)^(INT((A36-1)/12)) -> 3204.8021 | O36: =(M36-N36) -> 326762.34
A37: 36 | B37: 46746 | C37: =(45*35000*(1+0.03)^(INT((A37-1)/12)))/12 -> 139243.12 | D37: =(41 * 30000) / 12 + IF((410 * 30000) > 9800000, ((410 * 30000) - 9800000) * 0.1 / 12, 0) -> 123333.33 | E37: =IF(A36<=36, (29 * 50000) / 12, IF(A36<=42, 0, (29 * 50000) / 12)) -> 120833.33 | F37: =IF(A37 >= 57, (50 * 30000) / 12, IF(A37 >= 6, (42 * 30000) / 12, 0)) -> 105000 | G37: =SUM(C37:F37) -> 488409.79 | H37: =IF(A37 >= 1, ((15.8 - 10) * 35000 / 12), 0) + IF(A37 <= 36, (15.8 * 50000 / 12), 0) + IF(A37 >= 6, ((15.8 - 11.5) * 30000 / 12), 0) -> 93500 | I37: =G37+H37 -> 581909.79 | J37: =(I37*0.1) -> 58190.979 | K37: =I37-J37 -> 523718.81 | L37: =(15.8*145000/12)+(0.03*(F37-(0.1*F37))) -> 193751.67 | M37: =(K37-L37) -> 329967.15 | N37: =(0.25*145000/12)*(1+3%)^(INT((A37-1)/12)) -> 3204.8021 | O37: =(M37-N37) -> 326762.34
A38: 37 | B38: 46777 | C38: =(45*35000*(1+0.03)^(INT((A38-1)/12)))/12 -> 143420.42 | D38: =(41 * 30000) / 12 + IF((265 * 30000) > 9800000, ((265 * 30000) - 9800000) * 0.1 / 12, 0) -> 102500 | E38: 0 | F38: =IF(A38 >= 57, (50 * 30000) / 12, IF(A38 >= 6, (42 * 30000) / 12, 0)) -> 105000 | G38: =SUM(C38:F38) -> 350920.42 | H38: =IF(A38 >= 1, ((15.8 - 10) * 35000 / 12), 0) + IF(A38 <= 36, (15.8 * 50000 / 12), 0) + IF(A38 >= 6, ((15.8 - 11.5) * 30000 / 12), 0) -> 27666.667 | I38: =G38+H38 -> 378587.09 | J38: =(I38*0.1) -> 37858.709 | K38: =I38-J38 -> 340728.38 | L38: =(15.8*145000/12)+(0.03*(F38-(0.1*F38))) -> 193751.67 | M38: =(K38-L38) -> 146976.71 | N38: =(0.25*145000/12)*(1+3%)^(INT((A38-1)/12)) -> 3300.9461 | O38: =(M38-N38) -> 143675.76
A39: 38 | B39: 46808 | C39: =(45*35000*(1+0.03)^(INT((A39-1)/12)))/12 -> 143420.42 | D39: =(41 * 30000) / 12 + IF((265 * 30000) > 9800000, ((265 * 30000) - 9800000) * 0.1 / 12, 0) -> 102500 | E39: 0 | F39: =IF(A39 >= 57, (50 * 30000) / 12, IF(A39 >= 6, (42 * 30000) / 12, 0)) -> 105000 | G39: =SUM(C39:F39) -> 350920.42 | H39: =IF(A39 >= 1, ((15.8 - 10) * 35000 / 12), 0) + IF(A39 <= 36, (15.8 * 50000 / 12), 0) + IF(A39 >= 6, ((15.8 - 11.5) * 30000 / 12), 0) -> 27666.667 | I39: =G39+H39 -> 378587.09 | J39: =(I39*0.1) -> 37858.709 | K39: =I39-J39 -> 340728.38 | L39: =(15.8*145000/12)+(0.03*(F39-(0.1*F39))) -> 193751.67 | M39: =(K39-L39) -> 146976.71 | N39: =(0.25*145000/12)*(1+3%)^(INT((A39-1)/12)) -> 3300.9461 | O39: =(M39-N39) -> 143675.76
A40: 39 | B40: 46837 | C40: =(45*35000*(1+0.03)^(INT((A40-1)/12)))/12 -> 143420.42 | D40: =(41 * 30000) / 12 + IF((265 * 30000) > 9800000, ((265 * 30000) - 9800000) * 0.1 / 12, 0) -> 102500 | E40: 0 | F40: =IF(A40 >= 57, (50 * 30000) / 12, IF(A40 >= 6, (42 * 30000) / 12, 0)) -> 105000 | G40: =SUM(C40:F40) -> 350920.42 | H40: =IF(A40 >= 1, ((15.8 - 10) * 35000 / 12), 0) + IF(A40 <= 36, (15.8 * 50000 / 12), 0) + IF(A40 >= 6, ((15.8 - 11.5) * 30000 / 12), 0) -> 27666.667 | I40: =G40+H40 -> 378587.09 | J40: =(I40*0.1) -> 37858.709 | K40: =I40-J40 -> 340728.38 | L40: =(15.8*145000/12)+(0.03*(F40-(0.1*F40))) -> 193751.67 | M40: =(K40-L40) -> 146976.71 | N40: =(0.25*145000/12)*(1+3%)^(INT((A40-1)/12)) -> 3300.9461 | O40: =(M40-N40) -> 143675.76
A41: 40 | B41: 46868 | C41: =(45*35000*(1+0.03)^(INT((A41-1)/12)))/12 -> 143420.42 | D41: =(41 * 30000) / 12 + IF((265 * 30000) > 9800000, ((265 * 30000) - 9800000) * 0.1 / 12, 0) -> 102500 | E41: 0 | F41: =IF(A41 >= 57, (50 * 30000) / 12, IF(A41 >= 6, (42 * 30000) / 12, 0)) -> 105000 | G41: =SUM(C41:F41) -> 350920.42 | H41: =IF(A41 >= 1, ((15.8 - 10) * 35000 / 12), 0) + IF(A41 <= 36, (15.8 * 50000 / 12), 0) + IF(A41 >= 6, ((15.8 - 11.5) * 30000 / 12), 0) -> 27666.667 | I41: =G41+H41 -> 378587.09 | J41: =(I41*0.1) -> 37858.709 | K41: =I41-J41 -> 340728.38 | L41: =(15.8*145000/12)+(0.03*(F41-(0.1*F41))) -> 193751.67 | M41: =(K41-L41) -> 146976.71 | N41: =(0.25*145000/12)*(1+3%)^(INT((A41-1)/12)) -> 3300.9461 | O41: =(M41-N41) -> 143675.76
A42: 41 | B42: 46898 | C42: =(45*35000*(1+0.03)^(INT((A42-1)/12)))/12 -> 143420.42 | D42: =(41 * 30000) / 12 + IF((265 * 30000) > 9800000, ((265 * 30000) - 9800000) * 0.1 / 12, 0) -> 102500 | E42: 0 | F42: =IF(A42 >= 57, (50 * 30000) / 12, IF(A42 >= 6, (42 * 30000) / 12, 0)) -> 105000 | G42: =SUM(C42:F42) -> 350920.42 | H42: =IF(A42 >= 1, ((15.8 - 10) * 35000 / 12), 0) + IF(A42 <= 36, (15.8 * 50000 / 12), 0) + IF(A42 >= 6, ((15.8 - 11.5) * 30000 / 12), 0) -> 27666.667 | I42: =G42+H42 -> 378587.09 | J42: =(I42*0.1) -> 37858.709 | K42: =I42-J42 -> 340728.38 | L42: =(15.8*145000/12)+(0.03*(F42-(0.1*F42))) -> 193751.67 | M42: =(K42-L42) -> 146976.71 | N42: =(0.25*145000/12)*(1+3%)^(INT((A42-1)/12)) -> 3300.9461 | O42: =(M42-N42) -> 143675.76
A43: 42 | B43: 46929 | C43: =(45*35000*(1+0.03)^(INT((A43-1)/12)))/12 -> 143420.42 | D43: =(41 * 30000) / 12 + IF((265 * 30000) > 9800000, ((265 * 30000) - 9800000) * 0.1 / 12, 0) -> 102500 | E43: 0 | F43: =IF(A43 >= 57, (50 * 30000) / 12, IF(A43 >= 6, (42 * 30000) / 12, 0)) -> 105000 | G43: =SUM(C43:F43) -> 350920.42 | H43: =IF(A43 >= 1, ((15.8 - 10) * 35000 / 12), 0) + IF(A43 <= 36, (15.8 * 50000 / 12), 0) + IF(A43 >= 6, ((15.8 - 11.5) * 30000 / 12), 0) -> 27666.667 | I43: =G43+H43 -> 378587.09 | J43: =(I43*0.1) -> 37858.709 | K43: =I43-J43 -> 340728.38 | L43: =(15.8*145000/12)+(0.03*(F43-(0.1*F43))) -> 193751.67 | M43: =(K43-L43) -> 146976.71 | N43: =(0.25*145000/12)*(1+3%)^(INT((A43-1)/12)) -> 3300.9461 | O43: =(M43-N43) -> 143675.76
A44: 43 | B44: 46959 | C44: =(45*35000*(1+0.03)^(INT((A44-1)/12)))/12 -> 143420.42 | D44: =(41 * 30000) / 12 + IF((265 * 30000) > 9800000, ((265 * 30000) - 9800000) * 0.1 / 12, 0) -> 102500 | E44: =(30*(1+0.03)^3)*50000/12 -> 136590.88 | F44: =IF(A44 >= 57, (50 * 30000) / 12, IF(A44 >= 6, (42 * 30000) / 12, 0)) -> 105000 | G44: =SUM(C44:F44) -> 487511.29 | H44: =IF(A44 >= 1, ((15.8 - 10) * 35000 / 12), 0) + IF(A44 <= 36, (15.8 * 50000 / 12), 0) + IF(A44 >= 6, ((15.8 - 11.5) * 30000 / 12), 0) -> 27666.667 | I44: =G44+H44 -> 515177.96 | J44: =(I44*0.1) -> 51517.796 | K44: =I44-J44 -> 463660.16 | L44: =(15.8*145000/12)+(0.03*(F44-(0.1*F44))) -> 193751.67 | M44: =(K44-L44) -> 269908.5 | N44: =(0.25*145000/12)*(1+3%)^(INT((A44-1)/12)) -> 3300.9461 | O44: =(M44-N44) -> 266607.55
A45: 44 | B45: 46990 | C45: =(45*35000*(1+0.03)^(INT((A45-1)/12)))/12 -> 143420.42 | D45: =(41 * 30000) / 12 + IF((265 * 30000) > 9800000, ((265 * 30000) - 9800000) * 0.1 / 12, 0) -> 102500 | E45: =(30*(1+0.03)^3)*50000/12 -> 136590.88 | F45: =IF(A45 >= 57, (50 * 30000) / 12, IF(A45 >= 6, (42 * 30000) / 12, 0)) -> 105000 | G45: =SUM(C45:F45) -> 487511.29 | H45: =IF(A45 >= 1, ((15.8 - 10) * 35000 / 12), 0) + IF(A45 <= 36, (15.8 * 50000 / 12), 0) + IF(A45 >= 6, ((15.8 - 11.5) * 30000 / 12), 0) -> 27666.667 | I45: =G45+H45 -> 515177.96 | J45: =(I45*0.1) -> 51517.796 | K45: =I45-J45 -> 463660.16 | L45: =(15.8*145000/12)+(0.03*(F45-(0.1*F45))) -> 193751.67 | M45: =(K45-L45) -> 269908.5 | N45: =(0.25*145000/12)*(1+3%)^(INT((A45-1)/12)) -> 3300.9461 | O45: =(M45-N45) -> 266607.55
A46: 45 | B46: 47021 | C46: =(45*35000*(1+0.03)^(INT((A46-1)/12)))/12 -> 143420.42 | D46: =(41 * 30000) / 12 + IF((265 * 30000) > 9800000, ((265 * 30000) - 9800000) * 0.1 / 12, 0) -> 102500 | E46: =(30*(1+0.03)^3)*50000/12 -> 136590.88 | F46: =IF(A46 >= 57, (50 * 30000) / 12, IF(A46 >= 6, (42 * 30000) / 12, 0)) -> 105000 | G46: =SUM(C46:F46) -> 487511.29 | H46: =IF(A46 >= 1, ((15.8 - 10) * 35000 / 12), 0) + IF(A46 <= 36, (15.8 * 50000 / 12), 0) + IF(A46 >= 6, ((15.8 - 11.5) * 30000 / 12), 0) -> 27666.667 | I46: =G46+H46 -> 515177.96 | J46: =(I46*0.1) -> 51517.796 | K46: =I46-J46 -> 463660.16 | L46: =(15.8*145000/12)+(0.03*(F46-(0.1*F46))) -> 193751.67 | M46: =(K46-L46) -> 269908.5 | N46: =(0.25*145000/12)*(1+3%)^(INT((A46-1)/12)) -> 3300.9461 | O46: =(M46-N46) -> 266607.55
A47: 46 | B47: 47051 | C47: =(45*35000*(1+0.03)^(INT((A47-1)/12)))/12 -> 143420.42 | D47: =(41 * 30000) / 12 + IF((265 * 30000) > 9800000, ((265 * 30000) - 9800000) * 0.1 / 12, 0) -> 102500 | E47: =(30*(1+0.03)^3)*50000/12 -> 136590.88 | F47: =IF(A47 >= 57, (50 * 30000) / 12, IF(A47 >= 6, (42 * 30000) / 12, 0)) -> 105000 | G47: =SUM(C47:F47) -> 487511.29 | H47: =IF(A47 >= 1, ((15.8 - 10) * 35000 / 12), 0) + IF(A47 <= 36, (15.8 * 50000 / 12), 0) + IF(A47 >= 6, ((15.8 - 11.5) * 30000 / 12), 0) -> 27666.667 | I47: =G47+H47 -> 515177.96 | J47: =(I47*0.1) -> 51517.796 | K47: =I47-J47 -> 463660.16 | L47: =(15.8*145000/12)+(0.03*(F47-(0.1*F47))) -> 193751.67 | M47: =(K47-L47) -> 269908.5 | N47: =(0.25*145000/12)*(1+3%)^(INT((A47-1)/12)) -> 3300.9461 | O47: =(M47-N47) -> 266607.55
A48: 47 | B48: 47082 | C48: =(45*35000*(1+0.03)^(INT((A48-1)/12)))/12 -> 143420.42 | D48: =(41 * 30000) / 12 + IF((265 * 30000) > 9800000, ((265 * 30000) - 9800000) * 0.1 / 12, 0) -> 102500 | E48: =(30*(1+0.03)^3)*50000/12 -> 136590.88 | F48: =IF(A48 >= 57, (50 * 30000) / 12, IF(A48 >= 6, (42 * 30000) / 12, 0)) -> 105000 | G48: =SUM(C48:F48) -> 487511.29 | H48: =IF(A48 >= 1, ((15.8 - 10) * 35000 / 12), 0) + IF(A48 <= 36, (15.8 * 50000 / 12), 0) + IF(A48 >= 6, ((15.8 - 11.5) * 30000 / 12), 0) -> 27666.667 | I48: =G48+H48 -> 515177.96 | J48: =(I48*0.1) -> 51517.796 | K48: =I48-J48 -> 463660.16 | L48: =(15.8*145000/12)+(0.03*(F48-(0.1*F48))) -> 193751.67 | M48: =(K48-L48) -> 269908.5 | N48: =(0.25*145000/12)*(1+3%)^(INT((A48-1)/12)) -> 3300.9461 | O48: =(M48-N48) -> 266607.55
A49: 48 | B49: 47112 | C49: =(45*35000*(1+0.03)^(INT((A49-1)/12)))/12 -> 143420.42 | D49: =(41 * 30000) / 12 + IF((265 * 30000) > 9800000, ((265 * 30000) - 9800000) * 0.1 / 12, 0) -> 102500 | E49: =(30*(1+0.03)^3)*50000/12 -> 136590.88 | F49: =IF(A49 >= 57, (50 * 30000) / 12, IF(A49 >= 6, (42 * 30000) / 12, 0)) -> 105000 | G49: =SUM(C49:F49) -> 487511.29 | H49: =IF(A49 >= 1, ((15.8 - 10) * 35000 / 12), 0) + IF(A49 <= 36, (15.8 * 50000 / 12), 0) + IF(A49 >= 6, ((15.8 - 11.5) * 30000 / 12), 0) -> 27666.667 | I49: =G49+H49 -> 515177.96 | J49: =(I49*0.1) -> 51517.796 | K49: =I49-J49 -> 463660.16 | L49: =(15.8*145000/12)+(0.03*(F49-(0.1*F49))) -> 193751.67 | M49: =(K49-L49) -> 269908.5 | N49: =(0.25*145000/12)*(1+3%)^(INT((A49-1)/12)) -> 3300.9461 | O49: =(M49-N49) -> 266607.55
A50: 49 | B50: 47143 | C50: =(45*35000*(1+0.03)^(INT((A50-1)/12)))/12 -> 147723.03 | D50: =(41 * 30000) / 12 + IF((500 * 30000) > 9800000, ((500 * 30000) - 9800000) * 0.1 / 12, 0) -> 145833.33 | E50: =(30*(1+0.03)^3)*50000/12 -> 136590.88 | F50: =IF(A50 >= 57, (50 * 30000) / 12, IF(A50 >= 6, (42 * 30000) / 12, 0)) -> 105000 | G50: =SUM(C50:F50) -> 535147.24 | H50: =IF(A50 >= 1, ((15.8 - 10) * 35000 / 12), 0) + IF(A50 <= 36, (15.8 * 50000 / 12), 0) + IF(A50 >= 6, ((15.8 - 11.5) * 30000 / 12), 0) -> 27666.667 | I50: =G50+H50 -> 562813.91 | J50: =(I50*0.1) -> 56281.391 | K50: =I50-J50 -> 506532.52 | L50: =(15.8*145000/12)+(0.03*(F50-(0.1*F50))) -> 193751.67 | M50: =(K50-L50) -> 312780.85 | N50: =(0.25*145000/12)*(1+3%)^(INT((A50-1)/12)) -> 3399.9745 | O50: =(M50-N50) -> 309380.87
A51: 50 | B51: 47174 | C51: =(45*35000*(1+0.03)^(INT((A51-1)/12)))/12 -> 147723.03 | D51: =(41 * 30000) / 12 + IF((500 * 30000) > 9800000, ((500 * 30000) - 9800000) * 0.1 / 12, 0) -> 145833.33 | E51: =(30*(1+0.03)^3)*50000/12 -> 136590.88 | F51: =IF(A51 >= 57, (50 * 30000) / 12, IF(A51 >= 6, (42 * 30000) / 12, 0)) -> 105000 | G51: =SUM(C51:F51) -> 535147.24 | H51: =IF(A51 >= 1, ((15.8 - 10) * 35000 / 12), 0) + IF(A51 <= 36, (15.8 * 50000 / 12), 0) + IF(A51 >= 6, ((15.8 - 11.5) * 30000 / 12), 0) -> 27666.667 | I51: =G51+H51 -> 562813.91 | J51: =(I51*0.1) -> 56281.391 | K51: =I51-J51 -> 506532.52 | L51: =(15.8*145000/12)+(0.03*(F51-(0.1*F51))) -> 193751.67 | M51: =(K51-L51) -> 312780.85 | N51: =(0.25*145000/12)*(1+3%)^(INT((A51-1)/12)) -> 3399.9745 | O51: =(M51-N51) -> 309380.87
A52: 51 | B52: 47202 | C52: =(45*35000*(1+0.03)^(INT((A52-1)/12)))/12 -> 147723.03 | D52: =(41 * 30000) / 12 + IF((500 * 30000) > 9800000, ((500 * 30000) - 9800000) * 0.1 / 12, 0) -> 145833.33 | E52: =(30*(1+0.03)^3)*50000/12 -> 136590.88 | F52: =IF(A52 >= 57, (50 * 30000) / 12, IF(A52 >= 6, (42 * 30000) / 12, 0)) -> 105000 | G52: =SUM(C52:F52) -> 535147.24 | H52: =IF(A52 >= 1, ((15.8 - 10) * 35000 / 12), 0) + IF(A52 <= 36, (15.8 * 50000 / 12), 0) + IF(A52 >= 6, ((15.8 - 11.5) * 30000 / 12), 0) -> 27666.667 | I52: =G52+H52 -> 562813.91 | J52: =(I52*0.1) -> 56281.391 | K52: =I52-J52 -> 506532.52 | L52: =(15.8*145000/12)+(0.03*(F52-(0.1*F52))) -> 193751.67 | M52: =(K52-L52) -> 312780.85 | N52: =(0.25*145000/12)*(1+3%)^(INT((A52-1)/12)) -> 3399.9745 | O52: =(M52-N52) -> 309380.87
A53: 52 | B53: 47233 | C53: =(45*35000*(1+0.03)^(INT((A53-1)/12)))/12 -> 147723.03 | D53: =(41 * 30000) / 12 + IF((500 * 30000) > 9800000, ((500 * 30000) - 9800000) * 0.1 / 12, 0) -> 145833.33 | E53: =(30*(1+0.03)^3)*50000/12 -> 136590.88 | F53: =IF(A53 >= 57, (50 * 30000) / 12, IF(A53 >= 6, (42 * 30000) / 12, 0)) -> 105000 | G53: =SUM(C53:F53) -> 535147.24 | H53: =IF(A53 >= 1, ((15.8 - 10) * 35000 / 12), 0) + IF(A53 <= 36, (15.8 * 50000 / 12), 0) + IF(A53 >= 6, ((15.8 - 11.5) * 30000 / 12), 0) -> 27666.667 | I53: =G53+H53 -> 562813.91 | J53: =(I53*0.1) -> 56281.391 | K53: =I53-J53 -> 506532.52 | L53: =(15.8*145000/12)+(0.03*(F53-(0.1*F53))) -> 193751.67 | M53: =(K53-L53) -> 312780.85 | N53: =(0.25*145000/12)*(1+3%)^(INT((A53-1)/12)) -> 3399.9745 | O53: =(M53-N53) -> 309380.87
A54: 53 | B54: 47263 | C54: =(45*35000*(1+0.03)^(INT((A54-1)/12)))/12 -> 147723.03 | D54: =(41 * 30000) / 12 + IF((500 * 30000) > 9800000, ((500 * 30000) - 9800000) * 0.1 / 12, 0) -> 145833.33 | E54: =(30*(1+0.03)^3)*50000/12 -> 136590.88 | F54: =IF(A54 >= 57, (50 * 30000) / 12, IF(A54 >= 6, (42 * 30000) / 12, 0)) -> 105000 | G54: =SUM(C54:F54) -> 535147.24 | H54: =IF(A54 >= 1, ((15.8 - 10) * 35000 / 12), 0) + IF(A54 <= 36, (15.8 * 50000 / 12), 0) + IF(A54 >= 6, ((15.8 - 11.5) * 30000 / 12), 0) -> 27666.667 | I54: =G54+H54 -> 562813.91 | J54: =(I54*0.1) -> 56281.391 | K54: =I54-J54 -> 506532.52 | L54: =(15.8*145000/12)+(0.03*(F54-(0.1*F54))) -> 193751.67 | M54: =(K54-L54) -> 312780.85 | N54: =(0.25*145000/12)*(1+3%)^(INT((A54-1)/12)) -> 3399.9745 | O54: =(M54-N54) -> 309380.87
A55: 54 | B55: 47294 | C55: =(45*35000*(1+0.03)^(INT((A55-1)/12)))/12 -> 147723.03 | D55: =(41 * 30000) / 12 + IF((500 * 30000) > 9800000, ((500 * 30000) - 9800000) * 0.1 / 12, 0) -> 145833.33 | E55: =(30*(1+0.03)^3)*50000/12 -> 136590.88 | F55: =IF(A55 >= 57, (50 * 30000) / 12, IF(A55 >= 6, (42 * 30000) / 12, 0)) -> 105000 | G55: =SUM(C55:F55) -> 535147.24 | H55: =IF(A55 >= 1, ((15.8 - 10) * 35000 / 12), 0) + IF(A55 <= 36, (15.8 * 50000 / 12), 0) + IF(A55 >= 6, ((15.8 - 11.5) * 30000 / 12), 0) -> 27666.667 | I55: =G55+H55 -> 562813.91 | J55: =(I55*0.1) -> 56281.391 | K55: =I55-J55 -> 506532.52 | L55: =(15.8*145000/12)+(0.03*(F55-(0.1*F55))) -> 193751.67 | M55: =(K55-L55) -> 312780.85 | N55: =(0.25*145000/12)*(1+3%)^(INT((A55-1)/12)) -> 3399.9745 | O55: =(M55-N55) -> 309380.87
A56: 55 | B56: 47324 | C56: =(45*35000*(1+0.03)^(INT((A56-1)/12)))/12 -> 147723.03 | D56: =(41 * 30000) / 12 + IF((500 * 30000) > 9800000, ((500 * 30000) - 9800000) * 0.1 / 12, 0) -> 145833.33 | E56: =(30*(1+0.03)^3)*50000/12 -> 136590.88 | F56: =IF(A56 >= 57, (50 * 30000) / 12, IF(A56 >= 6, (42 * 30000) / 12, 0)) -> 105000 | G56: =SUM(C56:F56) -> 535147.24 | H56: =IF(A56 >= 1, ((15.8 - 10) * 35000 / 12), 0) + IF(A56 <= 36, (15.8 * 50000 / 12), 0) + IF(A56 >= 6, ((15.8 - 11.5) * 30000 / 12), 0) -> 27666.667 | I56: =G56+H56 -> 562813.91 | J56: =(I56*0.1) -> 56281.391 | K56: =I56-J56 -> 506532.52 | L56: =(15.8*145000/12)+(0.03*(F56-(0.1*F56))) -> 193751.67 | M56: =(K56-L56) -> 312780.85 | N56: =(0.25*145000/12)*(1+3%)^(INT((A56-1)/12)) -> 3399.9745 | O56: =(M56-N56) -> 309380.87
A57: 56 | B57: 47355 | C57: =(45*35000*(1+0.03)^(INT((A57-1)/12)))/12 -> 147723.03 | D57: =(41 * 30000) / 12 + IF((500 * 30000) > 9800000, ((500 * 30000) - 9800000) * 0.1 / 12, 0) -> 145833.33 | E57: =(30*(1+0.03)^3)*50000/12 -> 136590.88 | F57: =IF(A57 >= 57, (50 * 30000) / 12, IF(A57 >= 6, (42 * 30000) / 12, 0)) -> 105000 | G57: =SUM(C57:F57) -> 535147.24 | H57: =IF(A57 >= 1, ((15.8 - 10) * 35000 / 12), 0) + IF(A57 <= 36, (15.8 * 50000 / 12), 0) + IF(A57 >= 6, ((15.8 - 11.5) * 30000 / 12), 0) -> 27666.667 | I57: =G57+H57 -> 562813.91 | J57: =(I57*0.1) -> 56281.391 | K57: =I57-J57 -> 506532.52 | L57: =(15.8*145000/12)+(0.03*(F57-(0.1*F57))) -> 193751.67 | M57: =(K57-L57) -> 312780.85 | N57: =(0.25*145000/12)*(1+3%)^(INT((A57-1)/12)) -> 3399.9745 | O57: =(M57-N57) -> 309380.87
A58: 57 | B58: 47386 | C58: =(45*35000*(1+0.03)^(INT((A58-1)/12)))/12 -> 147723.03 | D58: =(41 * 30000) / 12 + IF((500 * 30000) > 9800000, ((500 * 30000) - 9800000) * 0.1 / 12, 0) -> 145833.33 | E58: =(30*(1+0.03)^3)*50000/12 -> 136590.88 | F58: =IF(A58 >= 57, (50 * 30000) / 12, IF(A58 >= 6, (42 * 30000) / 12, 0)) -> 125000 | G58: =SUM(C58:F58) -> 555147.24 | H58: =IF(A58 >= 1, ((15.8 - 10) * 35000 / 12), 0) + IF(A58 <= 36, (15.8 * 50000 / 12), 0) + IF(A58 >= 6, ((15.8 - 11.5) * 30000 / 12), 0) -> 27666.667 | I58: =G58+H58 -> 582813.91 | J58: =(I58*0.1) -> 58281.391 | K58: =I58-J58 -> 524532.52 | L58: =(15.8*145000/12)+(0.03*(F58-(0.1*F58))) -> 194291.67 | M58: =(K58-L58) -> 330240.85 | N58: =(0.25*145000/12)*(1+3%)^(INT((A58-1)/12)) -> 3399.9745 | O58: =(M58-N58) -> 326840.87
A59: 58 | B59: 47416 | C59: =(45*35000*(1+0.03)^(INT((A59-1)/12)))/12 -> 147723.03 | D59: =(41 * 30000) / 12 + IF((500 * 30000) > 9800000, ((500 * 30000) - 9800000) * 0.1 / 12, 0) -> 145833.33 | E59: =(30*(1+0.03)^3)*50000/12 -> 136590.88 | F59: =IF(A59 >= 57, (50 * 30000) / 12, IF(A59 >= 6, (42 * 30000) / 12, 0)) -> 125000 | G59: =SUM(C59:F59) -> 555147.24 | H59: =IF(A59 >= 1, ((15.8 - 10) * 35000 / 12), 0) + IF(A59 <= 36, (15.8 * 50000 / 12), 0) + IF(A59 >= 6, ((15.8 - 11.5) * 30000 / 12), 0) -> 27666.667 | I59: =G59+H59 -> 582813.91 | J59: =(I59*0.1) -> 58281.391 | K59: =I59-J59 -> 524532.52 | L59: =(15.8*145000/12)+(0.03*(F59-(0.1*F59))) -> 194291.67 | M59: =(K59-L59) -> 330240.85 | N59: =(0.25*145000/12)*(1+3%)^(INT((A59-1)/12)) -> 3399.9745 | O59: =(M59-N59) -> 326840.87
A60: 59 | B60: 47447 | C60: =(45*35000*(1+0.03)^(INT((A60-1)/12)))/12 -> 147723.03 | D60: =(41 * 30000) / 12 + IF((500 * 30000) > 9800000, ((500 * 30000) - 9800000) * 0.1 / 12, 0) -> 145833.33 | E60: =(30*(1+0.03)^3)*50000/12 -> 136590.88 | F60: =IF(A60 >= 57, (50 * 30000) / 12, IF(A60 >= 6, (42 * 30000) / 12, 0)) -> 125000 | G60: =SUM(C60:F60) -> 555147.24 | H60: =IF(A60 >= 1, ((15.8 - 10) * 35000 / 12), 0) + IF(A60 <= 36, (15.8 * 50000 / 12), 0) + IF(A60 >= 6, ((15.8 - 11.5) * 30000 / 12), 0) -> 27666.667 | I60: =G60+H60 -> 582813.91 | J60: =(I60*0.1) -> 58281.391 | K60: =I60-J60 -> 524532.52 | L60: =(15.8*145000/12)+(0.03*(F60-(0.1*F60))) -> 194291.67 | M60: =(K60-L60) -> 330240.85 | N60: =(0.25*145000/12)*(1+3%)^(INT((A60-1)/12)) -> 3399.9745 | O60: =(M60-N60) -> 326840.87
A61: 60 | B61: 47477 | C61: =(45*35000*(1+0.03)^(INT((A61-1)/12)))/12 -> 147723.03 | D61: =(41 * 30000) / 12 + IF((500 * 30000) > 9800000, ((500 * 30000) - 9800000) * 0.1 / 12, 0) -> 145833.33 | E61: =(30*(1+0.03)^3)*50000/12 -> 136590.88 | F61: =IF(A61 >= 57, (50 * 30000) / 12, IF(A61 >= 6, (42 * 30000) / 12, 0)) -> 125000 | G61: =SUM(C61:F61) -> 555147.24 | H61: =IF(A61 >= 1, ((15.8 - 10) * 35000 / 12), 0) + IF(A61 <= 36, (15.8 * 50000 / 12), 0) + IF(A61 >= 6, ((15.8 - 11.5) * 30000 / 12), 0) -> 27666.667 | I61: =G61+H61 -> 582813.91 | J61: =(I61*0.1) -> 58281.391 | K61: =I61-J61 -> 524532.52 | L61: =(15.8*145000/12)+(0.03*(F61-(0.1*F61))) -> 194291.67 | M61: =(K61-L61) -> 330240.85 | N61: =(0.25*145000/12)*(1+3%)^(INT((A61-1)/12)) -> 3399.9745 | O61: =(M61-N61) -> 326840.87
A62: 61 | B62: 47508 | C62: =(45 * 35000 * (1 + 0.03)^INT((A62-1)/12)) / 12 -> 152154.72 | D62: =IF(A62 >= 61, ((550 * 30000 - 9800000) * 0.1) / 12, 0) -> 55833.333 | E62: =(30*50000*(1+0.03)^((A62-43)/12))/12 -> 130666.98 | F62: =IF(A62 >= 57, (50 * 30000) / 12, IF(A62 >= 6, (42 * 30000) / 12, 0)) -> 125000 | G62: =SUM(C62:F62) -> 463655.03 | H62: =IF(A62 >= 1, ((15.8 - 10) * 35000 / 12), 0) + IF(A62 <= 36, (15.8 * 50000 / 12), 0) + IF(A62 >= 6, ((15.8 - 11.5) * 30000 / 12), 0) -> 27666.667 | I62: =G62+H62 -> 491321.7 | J62: =(I62*0.1) -> 49132.17 | K62: =I62-J62 -> 442189.53 | L62: =(15.8*145000/12)+(0.03*(F62-(0.1*F62))) -> 194291.67 | M62: =(K62-L62) -> 247897.86 | N62: =(0.25*145000/12)*(1+3%)^(INT((A62-1)/12)) -> 3501.9738 | O62: =(M62-N62) -> 244395.89
A63: 62 | B63: 47539 | C63: =(45 * 35000 * (1 + 0.03)^INT((A62-1)/12)) / 12 -> 152154.72 | D63: =IF(A63 >= 61, ((550 * 30000 - 9800000) * 0.1) / 12, 0) -> 55833.333 | E63: =(30*50000*(1+0.03)^((A63-43)/12))/12 -> 130989.24 | F63: =IF(A63 >= 57, (50 * 30000) / 12, IF(A63 >= 6, (42 * 30000) / 12, 0)) -> 125000 | G63: =SUM(C63:F63) -> 463977.29 | H63: =IF(A63 >= 1, ((15.8 - 10) * 35000 / 12), 0) + IF(A63 <= 36, (15.8 * 50000 / 12), 0) + IF(A63 >= 6, ((15.8 - 11.5) * 30000 / 12), 0) -> 27666.667 | I63: =G63+H63 -> 491643.96 | J63: =(I63*0.1) -> 49164.396 | K63: =I63-J63 -> 442479.57 | L63: =(15.8*145000/12)+(0.03*(F63-(0.1*F63))) -> 194291.67 | M63: =(K63-L63) -> 248187.9 | N63: =(0.25*145000/12)*(1+3%)^(INT((A63-1)/12)) -> 3501.9738 | O63: =(M63-N63) -> 244685.92
A64: 63 | B64: 47567 | C64: =(45 * 35000 * (1 + 0.03)^INT((A63-1)/12)) / 12 -> 152154.72 | D64: =IF(A64 >= 61, ((550 * 30000 - 9800000) * 0.1) / 12, 0) -> 55833.333 | E64: =(30*50000*(1+0.03)^((A64-43)/12))/12 -> 131312.29 | F64: =IF(A64 >= 57, (50 * 30000) / 12, IF(A64 >= 6, (42 * 30000) / 12, 0)) -> 125000 | G64: =SUM(C64:F64) -> 464300.35 | H64: =IF(A64 >= 1, ((15.8 - 10) * 35000 / 12), 0) + IF(A64 <= 36, (15.8 * 50000 / 12), 0) + IF(A64 >= 6, ((15.8 - 11.5) * 30000 / 12), 0) -> 27666.667 | I64: =G64+H64 -> 491967.02 | J64: =(I64*0.1) -> 49196.702 | K64: =I64-J64 -> 442770.31 | L64: =(15.8*145000/12)+(0.03*(F64-(0.1*F64))) -> 194291.67 | M64: =(K64-L64) -> 248478.65 | N64: =(0.25*145000/12)*(1+3%)^(INT((A64-1)/12)) -> 3501.9738 | O64: =(M64-N64) -> 244976.67
A65: 64 | B65: 47598 | C65: =(45 * 35000 * (1 + 0.03)^INT((A64-1)/12)) / 12 -> 152154.72 | D65: =IF(A65 >= 61, ((550 * 30000 - 9800000) * 0.1) / 12, 0) -> 55833.333 | E65: =(30*50000*(1+0.03)^((A65-43)/12))/12 -> 131636.15 | F65: =IF(A65 >= 57, (50 * 30000) / 12, IF(A65 >= 6, (42 * 30000) / 12, 0)) -> 125000 | G65: =SUM(C65:F65) -> 464624.2 | H65: =IF(A65 >= 1, ((15.8 - 10) * 35000 / 12), 0) + IF(A65 <= 36, (15.8 * 50000 / 12), 0) + IF(A65 >= 6, ((15.8 - 11.5) * 30000 / 12), 0) -> 27666.667 | I65: =G65+H65 -> 492290.87 | J65: =(I65*0.1) -> 49229.087 | K65: =I65-J65 -> 443061.78 | L65: =(15.8*145000/12)+(0.03*(F65-(0.1*F65))) -> 194291.67 | M65: =(K65-L65) -> 248770.11 | N65: =(0.25*145000/12)*(1+3%)^(INT((A65-1)/12)) -> 3501.9738 | O65: =(M65-N65) -> 245268.14
A66: 65 | B66: 47628 | C66: =(45 * 35000 * (1 + 0.03)^INT((A65-1)/12)) / 12 -> 152154.72 | D66: =IF(A66 >= 61, ((550 * 30000 - 9800000) * 0.1) / 12, 0) -> 55833.333 | E66: =(30*50000*(1+0.03)^((A66-43)/12))/12 -> 131960.8 | F66: =IF(A66 >= 57, (50 * 30000) / 12, IF(A66 >= 6, (42 * 30000) / 12, 0)) -> 125000 | G66: =SUM(C66:F66) -> 464948.85 | H66: =IF(A66 >= 1, ((15.8 - 10) * 35000 / 12), 0) + IF(A66 <= 36, (15.8 * 50000 / 12), 0) + IF(A66 >= 6, ((15.8 - 11.5) * 30000 / 12), 0) -> 27666.667 | I66: =G66+H66 -> 492615.52 | J66: =(I66*0.1) -> 49261.552 | K66: =I66-J66 -> 443353.97 | L66: =(15.8*145000/12)+(0.03*(F66-(0.1*F66))) -> 194291.67 | M66: =(K66-L66) -> 249062.3 | N66: =(0.25*145000/12)*(1+3%)^(INT((A66-1)/12)) -> 3501.9738 | O66: =(M66-N66) -> 245560.33
A67: 66 | B67: 47659 | C67: =(45 * 35000 * (1 + 0.03)^INT((A66-1)/12)) / 12 -> 152154.72 | D67: =IF(A67 >= 61, ((550 * 30000 - 9800000) * 0.1) / 12, 0) -> 55833.333 | E67: =(30*50000*(1+0.03)^((A67-43)/12))/12 -> 132286.25 | F67: =IF(A67 >= 57, (50 * 30000) / 12, IF(A67 >= 6, (42 * 30000) / 12, 0)) -> 125000 | G67: =SUM(C67:F67) -> 465274.3 | H67: =IF(A67 >= 1, ((15.8 - 10) * 35000 / 12), 0) + IF(A67 <= 36, (15.8 * 50000 / 12), 0) + IF(A67 >= 6, ((15.8 - 11.5) * 30000 / 12), 0) -> 27666.667 | I67: =G67+H67 -> 492940.97 | J67: =(I67*0.1) -> 49294.097 | K67: =I67-J67 -> 443646.87 | L67: =(15.8*145000/12)+(0.03*(F67-(0.1*F67))) -> 194291.67 | M67: =(K67-L67) -> 249355.21 | N67: =(0.25*145000/12)*(1+3%)^(INT((A67-1)/12)) -> 3501.9738 | O67: =(M67-N67) -> 245853.23
A68: 67 | B68: 47689 | C68: =(45 * 35000 * (1 + 0.03)^INT((A67-1)/12)) / 12 -> 152154.72 | D68: =IF(A68 >= 61, ((550 * 30000 - 9800000) * 0.1) / 12, 0) -> 55833.333 | E68: =(30*50000*(1+0.03)^((A68-43)/12))/12 -> 132612.5 | F68: =IF(A68 >= 57, (50 * 30000) / 12, IF(A68 >= 6, (42 * 30000) / 12, 0)) -> 125000 | G68: =SUM(C68:F68) -> 465600.56 | H68: =IF(A68 >= 1, ((15.8 - 10) * 35000 / 12), 0) + IF(A68 <= 36, (15.8 * 50000 / 12), 0) + IF(A68 >= 6, ((15.8 - 11.5) * 30000 / 12), 0) -> 27666.667 | I68: =G68+H68 -> 493267.22 | J68: =(I68*0.1) -> 49326.722 | K68: =I68-J68 -> 443940.5 | L68: =(15.8*145000/12)+(0.03*(F68-(0.1*F68))) -> 194291.67 | M68: =(K68-L68) -> 249648.83 | N68: =(0.25*145000/12)*(1+3%)^(INT((A68-1)/12)) -> 3501.9738 | O68: =(M68-N68) -> 246146.86
A69: 68 | B69: 47720 | C69: =(45 * 35000 * (1 + 0.03)^INT((A68-1)/12)) / 12 -> 152154.72 | D69: =IF(A69 >= 61, ((550 * 30000 - 9800000) * 0.1) / 12, 0) -> 55833.333 | E69: =(30*50000*(1+0.03)^((A69-43)/12))/12 -> 132939.56 | F69: =IF(A69 >= 57, (50 * 30000) / 12, IF(A69 >= 6, (42 * 30000) / 12, 0)) -> 125000 | G69: =SUM(C69:F69) -> 465927.61 | H69: =IF(A69 >= 1, ((15.8 - 10) * 35000 / 12), 0) + IF(A69 <= 36, (15.8 * 50000 / 12), 0) + IF(A69 >= 6, ((15.8 - 11.5) * 30000 / 12), 0) -> 27666.667 | I69: =G69+H69 -> 493594.28 | J69: =(I69*0.1) -> 49359.428 | K69: =I69-J69 -> 444234.85 | L69: =(15.8*145000/12)+(0.03*(F69-(0.1*F69))) -> 194291.67 | M69: =(K69-L69) -> 249943.19 | N69: =(0.25*145000/12)*(1+3%)^(INT((A69-1)/12)) -> 3501.9738 | O69: =(M69-N69) -> 246441.21
A70: 69 | B70: 47751 | C70: =(45 * 35000 * (1 + 0.03)^INT((A69-1)/12)) / 12 -> 152154.72 | D70: =IF(A70 >= 61, ((550 * 30000 - 9800000) * 0.1) / 12, 0) -> 55833.333 | E70: =(30*50000*(1+0.03)^((A70-43)/12))/12 -> 133267.42 | F70: =IF(A70 >= 57, (50 * 30000) / 12, IF(A70 >= 6, (42 * 30000) / 12, 0)) -> 125000 | G70: =SUM(C70:F70) -> 466255.48 | H70: =IF(A70 >= 1, ((15.8 - 10) * 35000 / 12), 0) + IF(A70 <= 36, (15.8 * 50000 / 12), 0) + IF(A70 >= 6, ((15.8 - 11.5) * 30000 / 12), 0) -> 27666.667 | I70: =G70+H70 -> 493922.15 | J70: =(I70*0.1) -> 49392.215 | K70: =I70-J70 -> 444529.93 | L70: =(15.8*145000/12)+(0.03*(F70-(0.1*F70))) -> 194291.67 | M70: =(K70-L70) -> 250238.26 | N70: =(0.25*145000/12)*(1+3%)^(INT((A70-1)/12)) -> 3501.9738 | O70: =(M70-N70) -> 246736.29
A71: 70 | B71: 47781 | C71: =(45 * 35000 * (1 + 0.03)^INT((A70-1)/12)) / 12 -> 152154.72 | D71: =IF(A71 >= 61, ((550 * 30000 - 9800000) * 0.1) / 12, 0) -> 55833.333 | E71: =(30*50000*(1+0.03)^((A71-43)/12))/12 -> 133596.1 | F71: =IF(A71 >= 57, (50 * 30000) / 12, IF(A71 >= 6, (42 * 30000) / 12, 0)) -> 125000 | G71: =SUM(C71:F71) -> 466584.15 | H71: =IF(A71 >= 1, ((15.8 - 10) * 35000 / 12), 0) + IF(A71 <= 36, (15.8 * 50000 / 12), 0) + IF(A71 >= 6, ((15.8 - 11.5) * 30000 / 12), 0) -> 27666.667 | I71: =G71+H71 -> 494250.82 | J71: =(I71*0.1) -> 49425.082 | K71: =I71-J71 -> 444825.74 | L71: =(15.8*145000/12)+(0.03*(F71-(0.1*F71))) -> 194291.67 | M71: =(K71-L71) -> 250534.07 | N71: =(0.25*145000/12)*(1+3%)^(INT((A71-1)/12)) -> 3501.9738 | O71: =(M71-N71) -> 247032.1
A72: 71 | B72: 47812 | C72: =(45 * 35000 * (1 + 0.03)^INT((A71-1)/12)) / 12 -> 152154.72 | D72: =IF(A72 >= 61, ((550 * 30000 - 9800000) * 0.1) / 12, 0) -> 55833.333 | E72: =(30*50000*(1+0.03)^((A72-43)/12))/12 -> 133925.58 | F72: =IF(A72 >= 57, (50 * 30000) / 12, IF(A72 >= 6, (42 * 30000) / 12, 0)) -> 125000 | G72: =SUM(C72:F72) -> 466913.64 | H72: =IF(A72 >= 1, ((15.8 - 10) * 35000 / 12), 0) + IF(A72 <= 36, (15.8 * 50000 / 12), 0) + IF(A72 >= 6, ((15.8 - 11.5) * 30000 / 12), 0) -> 27666.667 | I72: =G72+H72 -> 494580.3 | J72: =(I72*0.1) -> 49458.03 | K72: =I72-J72 -> 445122.27 | L72: =(15.8*145000/12)+(0.03*(F72-(0.1*F72))) -> 194291.67 | M72: =(K72-L72) -> 250830.61 | N72: =(0.25*145000/12)*(1+3%)^(INT((A72-1)/12)) -> 3501.9738 | O72: =(M72-N72) -> 247328.63
A73: 72 | B73: 47842 | C73: =(45 * 35000 * (1 + 0.03)^INT((A72-1)/12)) / 12 -> 152154.72 | D73: =IF(A73 >= 61, ((550 * 30000 - 9800000) * 0.1) / 12, 0) -> 55833.333 | E73: =(30*50000*(1+0.03)^((A73-43)/12))/12 -> 134255.88 | F73: =IF(A73 >= 57, (50 * 30000) / 12, IF(A73 >= 6, (42 * 30000) / 12, 0)) -> 125000 | G73: =SUM(C73:F73) -> 467243.93 | H73: =IF(A73 >= 1, ((15.8 - 10) * 35000 / 12), 0) + IF(A73 <= 36, (15.8 * 50000 / 12), 0) + IF(A73 >= 6, ((15.8 - 11.5) * 30000 / 12), 0) -> 27666.667 | I73: =G73+H73 -> 494910.6 | J73: =(I73*0.1) -> 49491.06 | K73: =I73-J73 -> 445419.54 | L73: =(15.8*145000/12)+(0.03*(F73-(0.1*F73))) -> 194291.67 | M73: =(K73-L73) -> 251127.87 | N73: =(0.25*145000/12)*(1+3%)^(INT((A73-1)/12)) -> 3501.9738 | O73: =(M73-N73) -> 247625.9

Sheet Annual Proforma
A1: Year | B1: Year 1 | C1: Year 2 | D1: Year 3 | E1: Year 4 | F1: Year 5 | G1: Reversion Year | I1: Equity IRR | J1: =J8*(1-0.7) -> 11359003
A2: PGI (Potential Gross Income) | B2: =SUM('Monthly Proforma'!I2:I13) -> 6058250 | C2: =SUM('Monthly Proforma'!I13:I25) -> 7307333.3 | D2: =SUM('Monthly Proforma'!I26:I37) -> 6982917.5 | E2: =SUM('Monthly Proforma'!I38:I49) -> 5362590.3 | F2: =SUM('Monthly Proforma'!I50:I61) -> 6833766.9 | G2: =F2*(1+0.03) -> 7038779.9 | I2: Debt Yield | J2: =B8/J14 -> 0.11310797
A3: Vacancy Loss (10%) | B3: =(B2*0.1) -> 605825 | C3: =(C2*0.1) -> 730733.33 | D3: =D2*0.1 -> 698291.75 | E3: =E2*0.1 -> 536259.03 | F3: =F2*0.1 -> 683376.69 | G3: =G2*0.1 -> 703877.99 | I3: Break-even Ratio | J3: =(B7+B11)/B2 -> 0.70324559
A4: EGI (Effective Gross Income) | B4: =B2-B3 -> 5452425 | C4: =C2-C3 -> 6576600 | D4: =D2-D3 -> 6284625.8 | E4: =E2-E3 -> 4826331.2 | F4: =F2-F3 -> 6150390.2 | G4: =G2-G3 -> 6334901.9 | I4: Cash-on-Cash Return | J4: =B12/J1 -> 0.10493768
A5: Expenses (Reimbursable) | B5: =145000*15.8 -> 2291000 | C5: =145000*16.274 -> 2359730 | D5: =145000*16.762 -> 2430490 | E5: =145000*17.265 -> 2503425 | F5: =145000*17.783 -> 2578535 | G5: =145000*18.316 -> 2655820
A6: Management Fee (3% of EGI) | B6: =B4*0.03 -> 163572.75 | C6: =C4*0.03 -> 197298 | D6: =D4*0.03 -> 188538.77 | E6: =E4*0.03 -> 144789.94 | F6: =F4*0.03 -> 184511.71 | G6: =G4*0.03 -> 190047.06
A7: Total Expenses | B7: =B5+B6 -> 2454572.8 | C7: =C5+C6 -> 2557028 | D7: =D5+D6 -> 2619028.8 | E7: =E5+E6 -> 2648214.9 | F7: =F5+F6 -> 2763046.7 | G7: =G5+G6 -> 2845867.1 | J7: =F8/0.085 -> 39851100
A8: NOI (Net Operating Income) | B8: =B4-B7 -> 2997852.2 | C8: =C4-C7 -> 4019572 | D8: =D4-D7 -> 3665597 | E8: =E4-E7 -> 2178116.3 | F8: =F4-F7 -> 3387343.5 | G8: =G4-G7 -> 3489034.8 | I8: Property Value | J8: =NPV(9.5%,B8,C8,D8,E8,F8+J7) -> 37863345
A9: Capital Reserves | B9: =145000*0.25*(1+0.03)^0 -> 36250 | C9: =145000*0.25*(1+0.03)^1 -> 37337.5 | D9: =145000*0.25*(1+0.03)^2 -> 38457.625 | E9: =145000*0.25*(1+0.03)^3 -> 39611.354 | F9: =145000*0.25*(1+0.03)^4 -> 40799.694 | G9: =145000*0.25*(1+0.03)^5 -> 42023.685 | I9: Loan-to-Value (LTV) | J9: =J8*70% -> 26504341
A10: Net Cash Flow (Pre-Debt) | B10: =B8-B9 -> 2961602.2 | C10: =C8-C9 -> 3982234.5 | D10: =D8-D9 -> 3627139.4 | E10: =E8-E9 -> 2138505 | F10: =F8-F9 -> 3346543.8 | G10: =G8-G9 -> 3447011.2 | I10: Loan Term (Years) | J10: =PMT(J13/12, 30*12, -J9) -> 150488.74
A11: Debt Service | B11: =J11 -> 1805864.8 | C11: =J11 -> 1805864.8 | D11: =J11 -> 1805864.8 | E11: =J11 -> 1805864.8 | F11: =J11 -> 1805864.8 | G11: =J11 -> 1805864.8 | I11: Annual Debt Service | J11: =J10*12 -> 1805864.8
A12: Cash Flow After Debt Service | B12: =B8-B11 -> 1191987.4 | C12: =C8-C11 -> 2213707.2 | D12: =D8-D11 -> 1859732.2 | E12: =E8-E11 -> 372251.48 | F12: =F8-F11 -> 1581478.7 | G12: =G10-G11 -> 1641146.3 | I12: Amortization Period (Years) | J12: 30
A13: Reversion Value | G13: =41047469+1540676.96 -> 42588146 | I13: Interest Rate (Annual) | J13: 0.055
A14: Total Cash Flow (Reversion Year) | B14: =B10-B11 -> 1155737.4 | C14: =C10-C11 -> 2176369.7 | D14: =D10-D11 -> 1821274.5 | E14: =E10-E11 -> 332640.13 | F14: =F10-F11 -> 1540679 | G14: =(F10-F11+G13) -> 44128825 | I14: Loan ammount | J14: =J8*70% -> 26504341
I15: Mortgage Balance

Sheet Expenses
A1: Category | B1: Expense per SF
A2: Taxes | B2: 6.75
A3: R&M | B3: 1.8
A4: Insurance | B4: 1
A5: Utilities | B5: 3.5
A6: Payroll | B6: 1.25
A7: Security | B7: 1.05
A8: G&A | B8: 0.45
B9: =SUM(B2:B8) -> 15.8
